invokestatic Method org/lwjgl/opengl/GL11 glLightModel (ILjava/nio/FloatBuffer;)V
invokestatic Method org/lwjgl/opengl/GL11 glLightModeli (II)V
invokestatic Method org/lwjgl/opengl/GL11 glLightf (IIF)V
invokestatic Method org/lwjgl/opengl/GL11 glMaterialf (IIF)V
invokestatic Method org/lwjgl/opengl/GL11 glNormalPointer (ILjava/nio/FloatBuffer;)V
invokestatic Method org/lwjgl/opengl/GL11 glPrioritizeTextures (Ljava/nio/IntBuffer;Ljava/nio/FloatBuffer;)V
invokestatic Method org/lwjgl/opengl/GL11 glTexSubImage1D (IIIIIILjava/nio/ByteBuffer;)V
invokestatic Method org/lwjgl/opengl/GL11 glTexSubImage1D (IIIIIILjava/nio/ShortBuffer;)V
invokestatic Method org/lwjgl/opengl/GL11 glTexSubImage2D (IIIIIIIILjava/nio/FloatBuffer;)V
invokestatic Method org/lwjgl/opengl/GL11 glTexSubImage2D (IIIIIIIILjava/nio/ShortBuffer;)V

invokestatic Method org/lwjgl/opengl/GL12 glTexImage3D (IIIIIIIIILjava/nio/ByteBuffer;)V
invokestatic Method org/lwjgl/opengl/GL12 glTexSubImage3D (IIIIIIIIIILjava/nio/FloatBuffer;)V

invokestatic Method org/lwjgl/opengl/GL42 glTexStorage1D (IIII)V
invokestatic Method org/lwjgl/opengl/GL42 glTexStorage3D (IIIIII)V

invokestatic Method org/lwjgl/opengl/GL43 glDispatchCompute (III)V