.version 61 0 
.class public super com/fs/starfarer/Version 
.super java/lang/Object 
.implements com/fs/util/DoNotObfuscate 
.field public static final versionInfoForMods Lcom/fs/starfarer/launcher/ModManager$VersionInfo; 
.field public static final versionOnly Ljava/lang/String; = '0.98a-RC8' 
.field public static final versionString Ljava/lang/String; = 'Starsector 0.98a-RC8' 
.field private static renderer Lcom/fs/graphics/A/ooOOOOOOOOOOOOOOOOOOOOOOOOOOOOOOOOOOOOOOOOOOOOOOOOOOOOOOOOOOOOOOOOOOOOOOOOOOOOOOOOOOOOOOOOOOOOOOOOOOOOOOOOOOOOOOOOOOOOOOOOOOOOOOOOOOOOOOOOOOOOOOOOOOOOOOOOOOOOOOOOOOOOOOOOOOOOOOOOOOOOOOOOOOOOOOOOOOOOOOOOOOOOOOOOOOOOOOOOOOOOOOOOOOOOOOOOOOOOOOOOOOOOOOOOOOOOOO; 

.method static <clinit> : ()V 
    .code stack 3 locals 0 
L0:     new com/fs/starfarer/launcher/ModManager$VersionInfo 
L3:     dup 
L4:     ldc '0.98a-RC8' 
L6:     invokespecial Method com/fs/starfarer/launcher/ModManager$VersionInfo <init> (Ljava/lang/String;)V 
L9:     putstatic Field com/fs/starfarer/Version versionInfoForMods Lcom/fs/starfarer/launcher/ModManager$VersionInfo; 
L12:    return 
L13:    
    .end code 
.end method 

.method public static render : ()V 
    .code stack 7 locals 1 
L0:     ldc 'renderVersionAndIdle' 
L2:     invokestatic Method com/fs/starfarer/settings/StarfarerSettings class (Ljava/lang/String;)Z 
L5:     ifne L9 
L8:     return 

        .stack same 
L9:     invokestatic Method org/lwjgl/opengl/GL11 glPushMatrix ()V 
L12:    getstatic Field com/fs/starfarer/Version renderer Lcom/fs/graphics/A/ooOOOOOOOOOOOOOOOOOOOOOOOOOOOOOOOOOOOOOOOOOOOOOOOOOOOOOOOOOOOOOOOOOOOOOOOOOOOOOOOOOOOOOOOOOOOOOOOOOOOOOOOOOOOOOOOOOOOOOOOOOOOOOOOOOOOOOOOOOOOOOOOOOOOOOOOOOOOOOOOOOOOOOOOOOOOOOOOOOOOOOOOOOOOOOOOOOOOOOOOOOOOOOOOOOOOOOOOOOOOOOOOOOOOOOOOOOOOOOOOOOOOOOOOOOOOOOO; 
L15:    ldc 'Starsector 0.98a-RC8 FR6.8'
L17:    invokevirtual Method com/fs/graphics/A/ooOOOOOOOOOOOOOOOOOOOOOOOOOOOOOOOOOOOOOOOOOOOOOOOOOOOOOOOOOOOOOOOOOOOOOOOOOOOOOOOOOOOOOOOOOOOOOOOOOOOOOOOOOOOOOOOOOOOOOOOOOOOOOOOOOOOOOOOOOOOOOOOOOOOOOOOOOOOOOOOOOOOOOOOOOOOOOOOOOOOOOOOOOOOOOOOOOOOOOOOOOOOOOOOOOOOOOOOOOOOOOOOOOOOOOOOOOOOOOOOOOOOOOOOOOOOOOO 'Õ00000' (Ljava/lang/String;)F 
L20:    fstore_0 
L21:    getstatic Field com/fs/starfarer/Version renderer Lcom/fs/graphics/A/ooOOOOOOOOOOOOOOOOOOOOOOOOOOOOOOOOOOOOOOOOOOOOOOOOOOOOOOOOOOOOOOOOOOOOOOOOOOOOOOOOOOOOOOOOOOOOOOOOOOOOOOOOOOOOOOOOOOOOOOOOOOOOOOOOOOOOOOOOOOOOOOOOOOOOOOOOOOOOOOOOOOOOOOOOOOOOOOOOOOOOOOOOOOOOOOOOOOOOOOOOOOOOOOOOOOOOOOOOOOOOOOOOOOOOOOOOOOOOOOOOOOOOOOOOOOOOOO; 
L24:    iconst_1 
L25:    invokevirtual Method com/fs/graphics/A/ooOOOOOOOOOOOOOOOOOOOOOOOOOOOOOOOOOOOOOOOOOOOOOOOOOOOOOOOOOOOOOOOOOOOOOOOOOOOOOOOOOOOOOOOOOOOOOOOOOOOOOOOOOOOOOOOOOOOOOOOOOOOOOOOOOOOOOOOOOOOOOOOOOOOOOOOOOOOOOOOOOOOOOOOOOOOOOOOOOOOOOOOOOOOOOOOOOOOOOOOOOOOOOOOOOOOOOOOOOOOOOOOOOOOOOOOOOOOOOOOOOOOOOOOOOOOOOO Object (Z)V 
L28:    getstatic Field com/fs/starfarer/Version renderer Lcom/fs/graphics/A/ooOOOOOOOOOOOOOOOOOOOOOOOOOOOOOOOOOOOOOOOOOOOOOOOOOOOOOOOOOOOOOOOOOOOOOOOOOOOOOOOOOOOOOOOOOOOOOOOOOOOOOOOOOOOOOOOOOOOOOOOOOOOOOOOOOOOOOOOOOOOOOOOOOOOOOOOOOOOOOOOOOOOOOOOOOOOOOOOOOOOOOOOOOOOOOOOOOOOOOOOOOOOOOOOOOOOOOOOOOOOOOOOOOOOOOOOOOOOOOOOOOOOOOOOOOOOOOO; 
L31:    new java/awt/Color 
L34:    dup 
L35:    iconst_0 
L36:    iconst_0 
L37:    iconst_0 
L38:    bipush 100 
L40:    invokespecial Method java/awt/Color <init> (IIII)V 
L43:    invokevirtual Method com/fs/graphics/A/ooOOOOOOOOOOOOOOOOOOOOOOOOOOOOOOOOOOOOOOOOOOOOOOOOOOOOOOOOOOOOOOOOOOOOOOOOOOOOOOOOOOOOOOOOOOOOOOOOOOOOOOOOOOOOOOOOOOOOOOOOOOOOOOOOOOOOOOOOOOOOOOOOOOOOOOOOOOOOOOOOOOOOOOOOOOOOOOOOOOOOOOOOOOOOOOOOOOOOOOOOOOOOOOOOOOOOOOOOOOOOOOOOOOOOOOOOOOOOOOOOOOOOOOOOOOOOOO o00000 (Ljava/awt/Color;)V 
L46:    getstatic Field com/fs/starfarer/Version renderer Lcom/fs/graphics/A/ooOOOOOOOOOOOOOOOOOOOOOOOOOOOOOOOOOOOOOOOOOOOOOOOOOOOOOOOOOOOOOOOOOOOOOOOOOOOOOOOOOOOOOOOOOOOOOOOOOOOOOOOOOOOOOOOOOOOOOOOOOOOOOOOOOOOOOOOOOOOOOOOOOOOOOOOOOOOOOOOOOOOOOOOOOOOOOOOOOOOOOOOOOOOOOOOOOOOOOOOOOOOOOOOOOOOOOOOOOOOOOOOOOOOOOOOOOOOOOOOOOOOOOOOOOOOOOO; 
L49:    new java/awt/Color 
L52:    dup 
L53:    sipush 255 
L56:    sipush 255 
L59:    sipush 255 
L62:    bipush 100 
L64:    invokespecial Method java/awt/Color <init> (IIII)V 
L67:    invokevirtual Method com/fs/graphics/A/ooOOOOOOOOOOOOOOOOOOOOOOOOOOOOOOOOOOOOOOOOOOOOOOOOOOOOOOOOOOOOOOOOOOOOOOOOOOOOOOOOOOOOOOOOOOOOOOOOOOOOOOOOOOOOOOOOOOOOOOOOOOOOOOOOOOOOOOOOOOOOOOOOOOOOOOOOOOOOOOOOOOOOOOOOOOOOOOOOOOOOOOOOOOOOOOOOOOOOOOOOOOOOOOOOOOOOOOOOOOOOOOOOOOOOOOOOOOOOOOOOOOOOOOOOOOOOOO 'Ò00000' (Ljava/awt/Color;)V 
L70:    getstatic Field com/fs/starfarer/Version renderer Lcom/fs/graphics/A/ooOOOOOOOOOOOOOOOOOOOOOOOOOOOOOOOOOOOOOOOOOOOOOOOOOOOOOOOOOOOOOOOOOOOOOOOOOOOOOOOOOOOOOOOOOOOOOOOOOOOOOOOOOOOOOOOOOOOOOOOOOOOOOOOOOOOOOOOOOOOOOOOOOOOOOOOOOOOOOOOOOOOOOOOOOOOOOOOOOOOOOOOOOOOOOOOOOOOOOOOOOOOOOOOOOOOOOOOOOOOOOOOOOOOOOOOOOOOOOOOOOOOOOOOOOOOOOO; 
L73:    invokestatic Method com/fs/starfarer/settings/StarfarerSettings 'while.new' ()F 
L76:    fload_0 
L77:    fsub 
L78:    ldc +5.0f 
L80:    fsub 
L81:    invokestatic Method com/fs/starfarer/settings/StarfarerSettings 'öÒ0000' ()F 
L84:    fconst_1 
L85:    fmul 
L86:    fconst_1 
L87:    fdiv 
L88:    invokevirtual Method com/fs/graphics/A/ooOOOOOOOOOOOOOOOOOOOOOOOOOOOOOOOOOOOOOOOOOOOOOOOOOOOOOOOOOOOOOOOOOOOOOOOOOOOOOOOOOOOOOOOOOOOOOOOOOOOOOOOOOOOOOOOOOOOOOOOOOOOOOOOOOOOOOOOOOOOOOOOOOOOOOOOOOOOOOOOOOOOOOOOOOOOOOOOOOOOOOOOOOOOOOOOOOOOOOOOOOOOOOOOOOOOOOOOOOOOOOOOOOOOOOOOOOOOOOOOOOOOOOOOOOOOOOO 'ö00000' (FF)V 
L91:    getstatic Field com/fs/starfarer/Version renderer Lcom/fs/graphics/A/ooOOOOOOOOOOOOOOOOOOOOOOOOOOOOOOOOOOOOOOOOOOOOOOOOOOOOOOOOOOOOOOOOOOOOOOOOOOOOOOOOOOOOOOOOOOOOOOOOOOOOOOOOOOOOOOOOOOOOOOOOOOOOOOOOOOOOOOOOOOOOOOOOOOOOOOOOOOOOOOOOOOOOOOOOOOOOOOOOOOOOOOOOOOOOOOOOOOOOOOOOOOOOOOOOOOOOOOOOOOOOOOOOOOOOOOOOOOOOOOOOOOOOOOOOOOOOOO; 
L94:    invokevirtual Method com/fs/graphics/A/ooOOOOOOOOOOOOOOOOOOOOOOOOOOOOOOOOOOOOOOOOOOOOOOOOOOOOOOOOOOOOOOOOOOOOOOOOOOOOOOOOOOOOOOOOOOOOOOOOOOOOOOOOOOOOOOOOOOOOOOOOOOOOOOOOOOOOOOOOOOOOOOOOOOOOOOOOOOOOOOOOOOOOOOOOOOOOOOOOOOOOOOOOOOOOOOOOOOOOOOOOOOOOOOOOOOOOOOOOOOOOOOOOOOOOOOOOOOOOOOOOOOOOOOOOOOOOOO 'Õ00000' ()V 
L97:    invokestatic Method org/lwjgl/opengl/GL11 glPopMatrix ()V 
L100:   return 
L101:   
    .end code 
.end method 

.method public <init> : ()V 
    .code stack 4 locals 3 
L0:     aload_0 
L1:     invokespecial Method java/lang/Object <init> ()V 
L4:     getstatic Field com/fs/starfarer/settings/StarfarerSettings 'float.new' Ljava/lang/String; 
L7:     astore_1 
L8:     aload_1 
L9:     invokestatic Method com/fs/graphics/A/D 'Ò00000' (Ljava/lang/String;)Lcom/fs/graphics/A/F; 
L12:    astore_2 
L13:    aload_2 
L14:    ifnonnull L27 
L17:    new java/lang/RuntimeException 
L20:    dup 
L21:    ldc 'Error loading font in Version.class' 
L23:    invokespecial Method java/lang/RuntimeException <init> (Ljava/lang/String;)V 
L26:    athrow 

        .stack full 
            locals Object com/fs/starfarer/Version Object java/lang/String Object com/fs/graphics/A/F 
            stack 
        .end stack 
L27:    getstatic Field com/fs/starfarer/settings/StarfarerSettings 'ÖÒ0000' Z 
L30:    ifeq L49 
L33:    new com/fs/graphics/A/ooOOOOOOOOOOOOOOOOOOOOOOOOOOOOOOOOOOOOOOOOOOOOOOOOOOOOOOOOOOOOOOOOOOOOOOOOOOOOOOOOOOOOOOOOOOOOOOOOOOOOOOOOOOOOOOOOOOOOOOOOOOOOOOOOOOOOOOOOOOOOOOOOOOOOOOOOOOOOOOOOOOOOOOOOOOOOOOOOOOOOOOOOOOOOOOOOOOOOOOOOOOOOOOOOOOOOOOOOOOOOOOOOOOOOOOOOOOOOOOOOOOOOOOOOOOOOOO 
L36:    dup 
L37:    ldc 'Starsector 0.98a-RC8 FR6.8'
L39:    aload_2 
L40:    invokespecial Method com/fs/graphics/A/ooOOOOOOOOOOOOOOOOOOOOOOOOOOOOOOOOOOOOOOOOOOOOOOOOOOOOOOOOOOOOOOOOOOOOOOOOOOOOOOOOOOOOOOOOOOOOOOOOOOOOOOOOOOOOOOOOOOOOOOOOOOOOOOOOOOOOOOOOOOOOOOOOOOOOOOOOOOOOOOOOOOOOOOOOOOOOOOOOOOOOOOOOOOOOOOOOOOOOOOOOOOOOOOOOOOOOOOOOOOOOOOOOOOOOOOOOOOOOOOOOOOOOOOOOOOOOOO <init> (Ljava/lang/String;Lcom/fs/graphics/A/F;)V 
L43:    putstatic Field com/fs/starfarer/Version renderer Lcom/fs/graphics/A/ooOOOOOOOOOOOOOOOOOOOOOOOOOOOOOOOOOOOOOOOOOOOOOOOOOOOOOOOOOOOOOOOOOOOOOOOOOOOOOOOOOOOOOOOOOOOOOOOOOOOOOOOOOOOOOOOOOOOOOOOOOOOOOOOOOOOOOOOOOOOOOOOOOOOOOOOOOOOOOOOOOOOOOOOOOOOOOOOOOOOOOOOOOOOOOOOOOOOOOOOOOOOOOOOOOOOOOOOOOOOOOOOOOOOOOOOOOOOOOOOOOOOOOOOOOOOOOO; 
L46:    goto L62 

        .stack same 
L49:    new com/fs/graphics/A/ooOOOOOOOOOOOOOOOOOOOOOOOOOOOOOOOOOOOOOOOOOOOOOOOOOOOOOOOOOOOOOOOOOOOOOOOOOOOOOOOOOOOOOOOOOOOOOOOOOOOOOOOOOOOOOOOOOOOOOOOOOOOOOOOOOOOOOOOOOOOOOOOOOOOOOOOOOOOOOOOOOOOOOOOOOOOOOOOOOOOOOOOOOOOOOOOOOOOOOOOOOOOOOOOOOOOOOOOOOOOOOOOOOOOOOOOOOOOOOOOOOOOOOOOOOOOOOO 
L52:    dup 
L53:    ldc 'Starsector 0.98a-RC8p' 
L55:    aload_2 
L56:    invokespecial Method com/fs/graphics/A/ooOOOOOOOOOOOOOOOOOOOOOOOOOOOOOOOOOOOOOOOOOOOOOOOOOOOOOOOOOOOOOOOOOOOOOOOOOOOOOOOOOOOOOOOOOOOOOOOOOOOOOOOOOOOOOOOOOOOOOOOOOOOOOOOOOOOOOOOOOOOOOOOOOOOOOOOOOOOOOOOOOOOOOOOOOOOOOOOOOOOOOOOOOOOOOOOOOOOOOOOOOOOOOOOOOOOOOOOOOOOOOOOOOOOOOOOOOOOOOOOOOOOOOOOOOOOOOO <init> (Ljava/lang/String;Lcom/fs/graphics/A/F;)V 
L59:    putstatic Field com/fs/starfarer/Version renderer Lcom/fs/graphics/A/ooOOOOOOOOOOOOOOOOOOOOOOOOOOOOOOOOOOOOOOOOOOOOOOOOOOOOOOOOOOOOOOOOOOOOOOOOOOOOOOOOOOOOOOOOOOOOOOOOOOOOOOOOOOOOOOOOOOOOOOOOOOOOOOOOOOOOOOOOOOOOOOOOOOOOOOOOOOOOOOOOOOOOOOOOOOOOOOOOOOOOOOOOOOOOOOOOOOOOOOOOOOOOOOOOOOOOOOOOOOOOOOOOOOOOOOOOOOOOOOOOOOOOOOOOOOOOOO; 

        .stack same 
L62:    return 
L63:    
    .end code 
.end method 
.innerclasses 
    com/fs/starfarer/launcher/ModManager$VersionInfo com/fs/starfarer/launcher/ModManager VersionInfo public static 
.end innerclasses 
.end class 
