.version 61 0 
.class public super com/fs/starfarer/settings/StarfarerSettings 
.super java/lang/Object 
.field public static 'ÖÔ0000' Ljava/util/Map; .fieldattributes 
    .signature Ljava/util/Map<Ljava/lang/String;Ljava/lang/String;>; 
.end fieldattributes 
.field public static 'öO0000' F 
.field public static 'öØ0000' I 
.field public static 'öÖ0000' F 
.field private static 'Ö00000' Lorg/apache/log4j/Logger; 
.field public static final o00000 Ljava/lang/String; = 'graphics/fonts/small_fonts8.fnt' 
.field public static final 'Óo0000' Ljava/lang/String; = 'graphics/fonts/arial16bold.fnt' 
.field public static final 'ØÒ0000' Ljava/lang/String; = 'graphics/fonts/arial12bold.fnt' 
.field public static final 'Oô0000' Ljava/lang/String; = 'graphics/fonts/arial12bold.fnt' 
.field public static final 'while.String' Ljava/lang/String; = 'graphics/fonts/arial10.fnt' 
.field public static final 'ØÕ0000' Ljava/lang/String; = 'graphics/fonts/orbitron24aabold.fnt' 
.field public static final 'while.Object' Ljava/lang/String; = 'graphics/fonts/orbitron24aa.fnt' 
.field public static final 'ÔÓ0000' Ljava/lang/String; = 'graphics/fonts/orbitron20aabold.fnt' 
.field public static final 'ÓÖ0000' Ljava/lang/String; = 'graphics/fonts/orbitron20aa.fnt' 
.field public static final 'while.class' Ljava/lang/String; = 'graphics/fonts/orbitron20bold.fnt' 
.field public static final 'interface.super' Ljava/lang/String; = 'graphics/fonts/orbitron12.fnt' 
.field public static final 'null.new' Ljava/lang/String; = 'graphics/fonts/orbitron20aa.fnt' 
.field public static final 'class.String' Ljava/lang/String; = 'graphics/fonts/victor10.fnt' 
.field public static final 'ÓÕ0000' Ljava/lang/String; = 'graphics/fonts/victor12.fnt' 
.field public static final 'new.String' Ljava/lang/String; = 'graphics/fonts/victor14.fnt' 
.field public static final 'öÔ0000' Ljava/lang/String; = 'graphics/fonts/victor16.fnt' 
.field public static final 'öÓ0000' Ljava/lang/String; = 'graphics/fonts/victor21.fnt' 
.field public static final 'oÓ0000' Ljava/lang/String; = 'graphics/fonts/orbitron10.fnt' 
.field public static final 'õO0000' Ljava/lang/String; = 'graphics/fonts/orbitron12condensed.fnt' 
.field public static 'float.new' Ljava/lang/String; 
.field public static final 'oÒ0000' Ljava/lang/String; = 'graphics/fonts/insignia21LTaa.fnt' 
.field public static final 'ÔÕ0000' Ljava/lang/String; = 'graphics/fonts/insignia25LTaa.fnt' 
.field public static final 'öo0000' Ljava/lang/String; = 'graphics/fonts/insignia16.fnt' 
.field public static final 'ÖÕ0000' Ljava/lang/String; = 'graphics/fonts/insignia16a.fnt' 
.field public static final 'null.super' Ljava/lang/String; = 'graphics/fonts/orbitron24aa.fnt' 
.field public static final 'oÕ0000' Ljava/lang/String; = 'graphics/fonts/orbitron20bold.fnt' 
.field public static oO0000 Z 
.field private static 'õÒ0000' F 
.field private static 'new.return' F 
.field private static 'float.return' Z 
.field private static 'õo0000' Z 
.field private static 'OÒ0000' Z 
.field private static 'new.super' I 
.field private static volatile 'ÔO0000' Lcom/fs/starfarer/settings/A; 
.field private static 'õØ0000' Lorg/json/JSONObject; 
.field private static 'õÓ0000' Lorg/json/JSONObject; 
.field private static 'oØ0000' Lorg/json/JSONObject; 
.field private static 'null.class' Z 
.field private static 'OÕ0000' Z 
.field private static 'OØ0000' Z 
.field private static while Z 
.field private static 'null.return' Z 
.field private static 'ö00000' Z 
.field private static 'Øô0000' Z 
.field private static 'OÔ0000' Z 
.field private static 'class.class' Z 
.field private static 'õ00000' Z 
.field private static 'oô0000' Z 
.field private static new Z 
.field private static class Z 
.field private static 'öÒ0000' Z 
.field private static 'Ó00000' F 
.field private static 'interface.class' Ljava/lang/String; 
.field public static 'ÖÒ0000' Z 
.field private static volatile 'õÔ0000' F 
.field private static volatile 'Ôô0000' F 
.field private static volatile 'oÔ0000' Z 
.field private static 'interface' I 
.field private static 'ÔØ0000' F 
.field private static 'ÖÓ0000' F 
.field private static 'ÓO0000' F 
.field private static 'õÕ0000' F 
.field private static 'ÖØ0000' F 
.field private static 'class.super' F 
.field private static 'ØÓ0000' F 
.field public static 'float.Object' F 
.field private static null F 
.field private static 'oÖ0000' F 
.field private static 'ØO0000' F 
.field private static Oo0000 F 
.field private static 'ÔÒ0000' F 
.field private static 'null.String' F 
.field private static 'ÔÖ0000' F 
.field private static 'õÖ0000' F 
.field private static 'new.class' F 
.field private static 'Øo0000' F 
.field private static 'ØÖ0000' F 
.field private static 'ÓÔ0000' F 
.field private static 'ÖO0000' F 
.field private static 'interface.Object' F 
.field private static 'float.super' F 
.field private static 'while.super' F 
.field private static 'class.return' F 
.field private static 'new.new' F 
.field private static 'interface.String' F 
.field private static 'float.class' F 
.field private static 'float.String' F 
.field private static 'Óô0000' F 
.field private static 'interface.new' F 
.field private static 'class.Object' F 
.field private static OO0000 F 
.field private static 'ÓÓ0000' F 
.field private static 'new.Object' F 
.field private static 'ØØ0000' F 
.field private static 'OÓ0000' F 
.field private static 'ÔÔ0000' F 
.field private static 'õô0000' Ljava/util/Map; .fieldattributes 
    .signature Ljava/util/Map<Lcom/fs/starfarer/api/combat/ShipAPI$HullSize;Ljava/lang/Float;>; 
.end fieldattributes 
.field public static 'OÖ0000' Z 
.field private static 'while.new' F 
.field private static 'class.new' F 
.field private static 'öÕ0000' F 
.field public static 'Öo0000' Lcom/fs/starfarer/settings/StarfarerSettings$Oo; 
.field private static oo0000 Lcom/fs/starfarer/api/combat/CombatReadinessPlugin; 
.field private static 'Ô00000' Ljava/util/Map; .fieldattributes 
    .signature Ljava/util/Map<Ljava/lang/String;Ljava/lang/Object;>; 
.end fieldattributes 
.field private static 'ÖÖ0000' Ljava/util/Map; .fieldattributes 
    .signature Ljava/util/Map<Ljava/lang/String;Ljava/awt/Color;>; 
.end fieldattributes 
.field private static 'Ø00000' Ljava/util/Map; .fieldattributes 
    .signature Ljava/util/Map<Ljava/lang/String;Ljava/awt/Color;>; 
.end fieldattributes 
.field private static 'öô0000' Ljava/util/Map; .fieldattributes 
    .signature Ljava/util/Map<Ljava/lang/String;Ljava/lang/Float;>; 
.end fieldattributes 
.field private static float Ljava/util/Map; .fieldattributes 
    .signature Ljava/util/Map<Ljava/lang/String;Ljava/lang/Boolean;>; 
.end fieldattributes 
.field private static 'Öô0000' Z 
.field private static 'ÓÒ0000' Ljava/awt/Color; 
.field private static 'null.Object' Ljava/awt/Color; 
.field private static 'ÓØ0000' Ljava/awt/Color; 
.field private static 'ØÔ0000' Ljava/awt/Color; 
.field private static volatile synthetic 'Ôo0000' [I 

.method static <clinit> : ()V 
    .code stack 2 locals 0 
L0:     new java/util/HashMap 
L3:     dup 
L4:     invokespecial Method java/util/HashMap <init> ()V 
L7:     putstatic Field com/fs/starfarer/settings/StarfarerSettings 'ÖÔ0000' Ljava/util/Map; 
L10:    fconst_1 
L11:    putstatic Field com/fs/starfarer/settings/StarfarerSettings 'öO0000' F 
L14:    iconst_0 
L15:    putstatic Field com/fs/starfarer/settings/StarfarerSettings 'öØ0000' I 
L18:    fconst_1 
L19:    putstatic Field com/fs/starfarer/settings/StarfarerSettings 'öÖ0000' F 
L22:    getstatic Field com/fs/starfarer/settings/StarfarerSettings 'öÖ0000' F 
L25:    putstatic Field com/fs/graphics/A/ooOOOOOOOOOOOOOOOOOOOOOOOOOOOOOOOOOOOOOOOOOOOOOOOOOOOOOOOOOOOOOOOOOOOOOOOOOOOOOOOOOOOOOOOOOOOOOOOOOOOOOOOOOOOOOOOOOOOOOOOOOOOOOOOOOOOOOOOOOOOOOOOOOOOOOOOOOOOOOOOOOOOOOOOOOOOOOOOOOOOOOOOOOOOOOOOOOOOOOOOOOOOOOOOOOOOOOOOOOOOOOOOOOOOOOOOOOOOOOOOOOOOOOOOOOOOOOO 'OÓ0000' F 
L28:    ldc Class com/fs/starfarer/settings/StarfarerSettings 
L30:    invokestatic Method org/apache/log4j/Logger getLogger (Ljava/lang/Class;)Lorg/apache/log4j/Logger; 
L33:    putstatic Field com/fs/starfarer/settings/StarfarerSettings 'Ö00000' Lorg/apache/log4j/Logger; 
L36:    iconst_0 
L37:    putstatic Field com/fs/starfarer/settings/StarfarerSettings oO0000 Z 
L40:    iconst_0 
L41:    putstatic Field com/fs/starfarer/settings/StarfarerSettings 'õo0000' Z 
L44:    iconst_0 
L45:    putstatic Field com/fs/starfarer/settings/StarfarerSettings 'OÒ0000' Z 
L48:    bipush 32 
L50:    putstatic Field com/fs/starfarer/settings/StarfarerSettings 'new.super' I 
L53:    new com/fs/starfarer/settings/A 
L56:    dup 
L57:    invokespecial Method com/fs/starfarer/settings/A <init> ()V 
L60:    putstatic Field com/fs/starfarer/settings/StarfarerSettings 'ÔO0000' Lcom/fs/starfarer/settings/A; 
L63:    iconst_1 
L64:    putstatic Field com/fs/starfarer/settings/StarfarerSettings 'OØ0000' Z 
L67:    iconst_1 
L68:    putstatic Field com/fs/starfarer/settings/StarfarerSettings while Z 
L71:    iconst_1 
L72:    putstatic Field com/fs/starfarer/settings/StarfarerSettings 'null.return' Z 
L75:    iconst_1 
L76:    putstatic Field com/fs/starfarer/settings/StarfarerSettings 'ö00000' Z 
L79:    iconst_0 
L80:    putstatic Field com/fs/starfarer/settings/StarfarerSettings 'Øô0000' Z 
L83:    iconst_0 
L84:    putstatic Field com/fs/starfarer/settings/StarfarerSettings 'OÔ0000' Z 
L87:    iconst_0 
L88:    putstatic Field com/fs/starfarer/settings/StarfarerSettings 'class.class' Z 
L91:    iconst_0 
L92:    putstatic Field com/fs/starfarer/settings/StarfarerSettings 'õ00000' Z 
L95:    iconst_0 
L96:    putstatic Field com/fs/starfarer/settings/StarfarerSettings 'oô0000' Z 
L99:    iconst_1 
L100:   putstatic Field com/fs/starfarer/settings/StarfarerSettings new Z 
L103:   iconst_0 
L104:   putstatic Field com/fs/starfarer/settings/StarfarerSettings class Z 
L107:   iconst_1 
L108:   putstatic Field com/fs/starfarer/settings/StarfarerSettings 'öÒ0000' Z 
L111:   ldc +20.0f 
L113:   putstatic Field com/fs/starfarer/settings/StarfarerSettings 'Ó00000' F 
L116:   ldc 'normal' 
L118:   putstatic Field com/fs/starfarer/settings/StarfarerSettings 'interface.class' Ljava/lang/String; 
L121:   iconst_0 
L122:   putstatic Field com/fs/starfarer/settings/StarfarerSettings 'ÖÒ0000' Z 
L125:   ldc_w +0.5f 
L128:   putstatic Field com/fs/starfarer/settings/StarfarerSettings 'õÔ0000' F 
L131:   fconst_1 
L132:   putstatic Field com/fs/starfarer/settings/StarfarerSettings 'Ôô0000' F 
L135:   iconst_0 
L136:   putstatic Field com/fs/starfarer/settings/StarfarerSettings 'oÔ0000' Z 
L139:   sipush 200 
L142:   putstatic Field com/fs/starfarer/settings/StarfarerSettings 'interface' I 
L145:   fconst_1 
L146:   putstatic Field com/fs/starfarer/settings/StarfarerSettings 'float.Object' F 
L149:   ldc_w +0.30000001192092896f 
L152:   putstatic Field com/fs/starfarer/settings/StarfarerSettings 'ØÖ0000' F 
L155:   new java/util/HashMap 
L158:   dup 
L159:   invokespecial Method java/util/HashMap <init> ()V 
L162:   putstatic Field com/fs/starfarer/settings/StarfarerSettings 'õô0000' Ljava/util/Map; 
L165:   iconst_1 
L166:   putstatic Field com/fs/starfarer/settings/StarfarerSettings 'OÖ0000' Z 
L169:   aconst_null 
L170:   putstatic Field com/fs/starfarer/settings/StarfarerSettings 'Öo0000' Lcom/fs/starfarer/settings/StarfarerSettings$Oo; 
L173:   ldc_w 'com.fs.starfarer.settings.osx' 
L176:   invokestatic Method java/lang/System getProperty (Ljava/lang/String;)Ljava/lang/String; 
L179:   ifnull L186 
L182:   iconst_1 
L183:   goto L187 

        .stack same_extended 
L186:   iconst_0 

        .stack stack_1 Integer 
L187:   putstatic Field com/fs/starfarer/settings/StarfarerSettings 'null.class' Z 
L190:   ldc_w 'com.fs.starfarer.settings.linux' 
L193:   invokestatic Method java/lang/System getProperty (Ljava/lang/String;)Ljava/lang/String; 
L196:   ifnull L203 
L199:   iconst_1 
L200:   goto L204 

        .stack same 
L203:   iconst_0 

        .stack stack_1 Integer 
L204:   putstatic Field com/fs/starfarer/settings/StarfarerSettings 'OÕ0000' Z 
L207:   aconst_null 
L208:   putstatic Field com/fs/starfarer/settings/StarfarerSettings oo0000 Lcom/fs/starfarer/api/combat/CombatReadinessPlugin; 
L211:   new java/util/HashMap 
L214:   dup 
L215:   invokespecial Method java/util/HashMap <init> ()V 
L218:   putstatic Field com/fs/starfarer/settings/StarfarerSettings 'Ô00000' Ljava/util/Map; 
L221:   new java/util/HashMap 
L224:   dup 
L225:   invokespecial Method java/util/HashMap <init> ()V 
L228:   putstatic Field com/fs/starfarer/settings/StarfarerSettings 'ÖÖ0000' Ljava/util/Map; 
L231:   new java/util/HashMap 
L234:   dup 
L235:   invokespecial Method java/util/HashMap <init> ()V 
L238:   putstatic Field com/fs/starfarer/settings/StarfarerSettings 'Ø00000' Ljava/util/Map; 
L241:   new java/util/HashMap 
L244:   dup 
L245:   invokespecial Method java/util/HashMap <init> ()V 
L248:   putstatic Field com/fs/starfarer/settings/StarfarerSettings 'öô0000' Ljava/util/Map; 
L251:   new java/util/HashMap 
L254:   dup 
L255:   invokespecial Method java/util/HashMap <init> ()V 
L258:   putstatic Field com/fs/starfarer/settings/StarfarerSettings float Ljava/util/Map; 
L261:   iconst_1 
L262:   putstatic Field com/fs/starfarer/settings/StarfarerSettings 'Öô0000' Z 
L265:   aconst_null 
L266:   putstatic Field com/fs/starfarer/settings/StarfarerSettings 'ÓÒ0000' Ljava/awt/Color; 
L269:   aconst_null 
L270:   putstatic Field com/fs/starfarer/settings/StarfarerSettings 'null.Object' Ljava/awt/Color; 
L273:   aconst_null 
L274:   putstatic Field com/fs/starfarer/settings/StarfarerSettings 'ÓØ0000' Ljava/awt/Color; 
L277:   aconst_null 
L278:   putstatic Field com/fs/starfarer/settings/StarfarerSettings 'ØÔ0000' Ljava/awt/Color; 
L281:   return 
L282:   
    .end code 
.end method 

.method public <init> : ()V 
    .code stack 1 locals 1 
L0:     aload_0 
L1:     invokespecial Method java/lang/Object <init> ()V 
L4:     return 
L5:     
    .end code 
.end method 

.method public static 'oØ0000' : ()F 
    .code stack 1 locals 0 
L0:     invokestatic Method com/fs/starfarer/settings/StarfarerSettings 'class.Object' ()F 
L3:     freturn 
L4:     
    .end code 
.end method 

.method public static o00000 : (FI)V 
    .code stack 1 locals 2 
L0:     fload_0 
L1:     putstatic Field com/fs/starfarer/settings/StarfarerSettings 'öÖ0000' F 
L4:     getstatic Field com/fs/starfarer/settings/StarfarerSettings 'öÖ0000' F 
L7:     putstatic Field com/fs/graphics/A/ooOOOOOOOOOOOOOOOOOOOOOOOOOOOOOOOOOOOOOOOOOOOOOOOOOOOOOOOOOOOOOOOOOOOOOOOOOOOOOOOOOOOOOOOOOOOOOOOOOOOOOOOOOOOOOOOOOOOOOOOOOOOOOOOOOOOOOOOOOOOOOOOOOOOOOOOOOOOOOOOOOOOOOOOOOOOOOOOOOOOOOOOOOOOOOOOOOOOOOOOOOOOOOOOOOOOOOOOOOOOOOOOOOOOOOOOOOOOOOOOOOOOOOOOOOOOOOO 'OÓ0000' F 
L10:    iload_1 
L11:    putstatic Field com/fs/graphics/A/ooOOOOOOOOOOOOOOOOOOOOOOOOOOOOOOOOOOOOOOOOOOOOOOOOOOOOOOOOOOOOOOOOOOOOOOOOOOOOOOOOOOOOOOOOOOOOOOOOOOOOOOOOOOOOOOOOOOOOOOOOOOOOOOOOOOOOOOOOOOOOOOOOOOOOOOOOOOOOOOOOOOOOOOOOOOOOOOOOOOOOOOOOOOOOOOOOOOOOOOOOOOOOOOOOOOOOOOOOOOOOOOOOOOOOOOOOOOOOOOOOOOOOOOOOOOOOOO 'while.new' I 
L14:    return 
L15:    
    .end code 
.end method 

.method private static 'null.new' : ()Lorg/json/JSONObject; 
    .exceptions java/io/IOException org/json/JSONException 
    .code stack 2 locals 1 
L0:     new java/util/HashSet 
L3:     dup 
L4:     invokespecial Method java/util/HashSet <init> ()V 
L7:     astore_0 
L8:     aload_0 
L9:     ldc_w 'vsync' 
L12:    invokevirtual Method java/util/HashSet add (Ljava/lang/Object;)Z 
L15:    pop 
L16:    aload_0 
L17:    ldc_w 'refreshRate' 
L20:    invokevirtual Method java/util/HashSet add (Ljava/lang/Object;)Z 
L23:    pop 
L24:    aload_0 
L25:    ldc_w 'fps' 
L28:    invokevirtual Method java/util/HashSet add (Ljava/lang/Object;)Z 
L31:    pop 
L32:    aload_0 
L33:    ldc_w 'devMode' 
L36:    invokevirtual Method java/util/HashSet add (Ljava/lang/Object;)Z 
L39:    pop 
L40:    aload_0 
L41:    ldc_w 'godMode' 
L44:    invokevirtual Method java/util/HashSet add (Ljava/lang/Object;)Z 
L47:    pop 
L48:    aload_0 
L49:    ldc_w 'playtestingMode' 
L52:    invokevirtual Method java/util/HashSet add (Ljava/lang/Object;)Z 
L55:    pop 
L56:    aload_0 
L57:    ldc_w 'colorblindMode' 
L60:    invokevirtual Method java/util/HashSet add (Ljava/lang/Object;)Z 
L63:    pop 
L64:    aload_0 
L65:    ldc_w 'resolutionOverride' 
L68:    invokevirtual Method java/util/HashSet add (Ljava/lang/Object;)Z 
L71:    pop 
L72:    aload_0 
L73:    ldc_w 'forceAspectRatio' 
L76:    invokevirtual Method java/util/HashSet add (Ljava/lang/Object;)Z 
L79:    pop 
L80:    aload_0 
L81:    ldc_w 'autoturnMode' 
L84:    invokevirtual Method java/util/HashSet add (Ljava/lang/Object;)Z 
L87:    pop 
L88:    aload_0 
L89:    ldc_w 'showEnemyWaypoints' 
L92:    invokevirtual Method java/util/HashSet add (Ljava/lang/Object;)Z 
L95:    pop 
L96:    aload_0 
L97:    ldc_w 'windowLocationX' 
L100:   invokevirtual Method java/util/HashSet add (Ljava/lang/Object;)Z 
L103:   pop 
L104:   aload_0 
L105:   ldc_w 'windowLocationY' 
L108:   invokevirtual Method java/util/HashSet add (Ljava/lang/Object;)Z 
L111:   pop 
L112:   aload_0 
L113:   ldc_w 'undecoratedWindow' 
L116:   invokevirtual Method java/util/HashSet add (Ljava/lang/Object;)Z 
L119:   pop 
L120:   aload_0 
L121:   ldc_w 'enableSoundFilters' 
L124:   invokevirtual Method java/util/HashSet add (Ljava/lang/Object;)Z 
L127:   pop 
L128:   aload_0 
L129:   ldc_w 'allowAnyJavaVersion' 
L132:   invokevirtual Method java/util/HashSet add (Ljava/lang/Object;)Z 
L135:   pop 
L136:   aload_0 
L137:   ldc_w 'allowForceQuitInIronMode' 
L140:   invokevirtual Method java/util/HashSet add (Ljava/lang/Object;)Z 
L143:   pop 
L144:   aload_0 
L145:   ldc_w 'useDefaultMouseCursor' 
L148:   invokevirtual Method java/util/HashSet add (Ljava/lang/Object;)Z 
L151:   pop 
L152:   aload_0 
L153:   ldc_w 'queryMaxAASamples' 
L156:   invokevirtual Method java/util/HashSet add (Ljava/lang/Object;)Z 
L159:   pop 
L160:   aload_0 
L161:   ldc_w 'maxAASamples' 
L164:   invokevirtual Method java/util/HashSet add (Ljava/lang/Object;)Z 
L167:   pop 
L168:   aload_0 
L169:   ldc_w 'aaSamplesOverride' 
L172:   invokevirtual Method java/util/HashSet add (Ljava/lang/Object;)Z 
L175:   pop 
L176:   aload_0 
L177:   ldc_w 'screenScaleOverride' 
L180:   invokevirtual Method java/util/HashSet add (Ljava/lang/Object;)Z 
L183:   pop 
L184:   aload_0 
L185:   ldc_w 'refreshRateOverride' 
L188:   invokevirtual Method java/util/HashSet add (Ljava/lang/Object;)Z 
L191:   pop 
L192:   aload_0 
L193:   ldc_w 'baseMemoryRequired' 
L196:   invokevirtual Method java/util/HashSet add (Ljava/lang/Object;)Z 
L199:   pop 
L200:   aload_0 
L201:   ldc_w 'maxMemoryFractionOfTotal' 
L204:   invokevirtual Method java/util/HashSet add (Ljava/lang/Object;)Z 
L207:   pop 
L208:   aload_0 
L209:   ldc_w 'minMemoryMB' 
L212:   invokevirtual Method java/util/HashSet add (Ljava/lang/Object;)Z 
L215:   pop 
L216:   aload_0 
L217:   ldc_w 'maxMemoryMB' 
L220:   invokevirtual Method java/util/HashSet add (Ljava/lang/Object;)Z 
L223:   pop 
L224:   aload_0 
L225:   ldc_w 'allowJVMRestartFromLauncher' 
L228:   invokevirtual Method java/util/HashSet add (Ljava/lang/Object;)Z 
L231:   pop 
L232:   aload_0 
L233:   ldc_w 'allowJVMRestartFromLauncherInDevMode' 
L236:   invokevirtual Method java/util/HashSet add (Ljava/lang/Object;)Z 
L239:   pop 
L240:   aload_0 
L241:   ldc_w 'requireTypingDeleteToDeleteSave' 
L244:   invokevirtual Method java/util/HashSet add (Ljava/lang/Object;)Z 
L247:   pop 
L248:   ldc_w 'data/config/settings.json' 
L251:   aload_0 
L252:   invokestatic Method com/fs/starfarer/loading/LoadingUtils 'super' (Ljava/lang/String;Ljava/util/Set;)Lorg/json/JSONObject; 
L255:   areturn 
L256:   
    .end code 
.end method 

.method public static 'interface.String' : ()Z 
    .code stack 2 locals 0 
L0:     ldc_w 'os.name' 
L3:     invokestatic Method java/lang/System getProperty (Ljava/lang/String;)Ljava/lang/String; 
L6:     ldc_w 'Windows' 
L9:     invokevirtual Method java/lang/String contains (Ljava/lang/CharSequence;)Z 
L12:    ifeq L28 
L15:    ldc_w 'ProgramFiles(x86)' 
L18:    invokestatic Method java/lang/System getenv (Ljava/lang/String;)Ljava/lang/String; 
L21:    ifnonnull L26 
L24:    iconst_1 
L25:    ireturn 

        .stack same 
L26:    iconst_0 
L27:    ireturn 

        .stack same 
L28:    iconst_0 
L29:    ireturn 
L30:    
    .end code 
.end method 

.method public static 'ÓO0000' : ()Z 
    .code stack 1 locals 0 
L0:     getstatic Field com/fs/starfarer/settings/StarfarerSettings 'öÒ0000' Z 
L3:     ireturn 
L4:     
    .end code 
.end method 

.method public static OO0000 : (Z)V 
    .code stack 1 locals 1 
L0:     iload_0 
L1:     putstatic Field com/fs/starfarer/settings/StarfarerSettings 'öÒ0000' Z 
L4:     return 
L5:     
    .end code 
.end method 

.method public static 'Ô00000' : ()F 
    .code stack 1 locals 0 
L0:     getstatic Field com/fs/starfarer/settings/StarfarerSettings 'Ó00000' F 
L3:     freturn 
L4:     
    .end code 
.end method 

.method public static 'Ó00000' : (F)V 
    .code stack 1 locals 1 
L0:     fload_0 
L1:     putstatic Field com/fs/starfarer/settings/StarfarerSettings 'Ó00000' F 
L4:     return 
L5:     
    .end code 
.end method 

.method public static 'class.class' : ()Z 
    .code stack 1 locals 0 
L0:     ldc_w 'allowForceQuitInIronMode' 
L3:     invokestatic Method com/fs/starfarer/settings/StarfarerSettings class (Ljava/lang/String;)Z 
L6:     ireturn 
L7:     
    .end code 
.end method 

.method public static 'while.super' : ()Z 
    .code stack 1 locals 0 
L0:     getstatic Field com/fs/starfarer/settings/StarfarerSettings 'OÖ0000' Z 
L3:     ireturn 
L4:     
    .end code 
.end method 

.method public static o00000 : ()Lcom/fs/starfarer/loading/O0oO; 
    .code stack 2 locals 0 
L0:     ldc_w Class com/fs/starfarer/loading/O0oO 
L3:     ldc_w 'player' 
L6:     invokestatic Method com/fs/starfarer/loading/SpecStore o00000 (Ljava/lang/Class;Ljava/lang/String;)Ljava/lang/Object; 
L9:     checkcast com/fs/starfarer/loading/O0oO 
L12:    areturn 
L13:    
    .end code 
.end method 

.method public static 'interface' : (Z)V 
    .code stack 1 locals 1 
L0:     iload_0 
L1:     putstatic Field com/fs/starfarer/settings/StarfarerSettings 'OÖ0000' Z 
L4:     return 
L5:     
    .end code 
.end method 

.method public static new : ()Z 
    .code stack 1 locals 0 
L0:     getstatic Field com/fs/starfarer/settings/StarfarerSettings 'oÔ0000' Z 
L3:     ireturn 
L4:     
    .end code 
.end method 

.method public static 'new.return' : ()F 
    .code stack 1 locals 0 
L0:     getstatic Field com/fs/starfarer/settings/StarfarerSettings 'ØÖ0000' F 
L3:     freturn 
L4:     
    .end code 
.end method 

.method public static o00000 : (F)V 
    .code stack 1 locals 1 
L0:     fload_0 
L1:     putstatic Field com/fs/starfarer/settings/StarfarerSettings 'ØÖ0000' F 
L4:     return 
L5:     
    .end code 
.end method 

.method public static 'ÓO0000' : (Z)V 
    .code stack 1 locals 1 
L0:     iload_0 
L1:     putstatic Field com/fs/starfarer/settings/StarfarerSettings 'oÔ0000' Z 
L4:     return 
L5:     
    .end code 
.end method 

.method public static 'öÔ0000' : ()V 
    .exceptions java/io/IOException org/json/JSONException 
    .code stack 3 locals 0 
L0:     getstatic Field com/fs/starfarer/settings/StarfarerSettings 'Ö00000' Lorg/apache/log4j/Logger; 
L3:     ldc_w 'Loading settings' 
L6:     invokevirtual Method org/apache/log4j/Logger info (Ljava/lang/Object;)V 
L9:     invokestatic Method com/fs/starfarer/settings/StarfarerSettings 'null.new' ()Lorg/json/JSONObject; 
L12:    putstatic Field com/fs/starfarer/settings/StarfarerSettings 'õØ0000' Lorg/json/JSONObject; 
L15:    getstatic Field com/fs/starfarer/settings/StarfarerSettings 'õØ0000' Lorg/json/JSONObject; 
L18:    ldc_w 'graphics' 
L21:    invokevirtual Method org/json/JSONObject getJSONObject (Ljava/lang/String;)Lorg/json/JSONObject; 
L24:    putstatic Field com/fs/starfarer/settings/StarfarerSettings 'õÓ0000' Lorg/json/JSONObject; 
L27:    getstatic Field com/fs/starfarer/settings/StarfarerSettings 'õØ0000' Lorg/json/JSONObject; 
L30:    ldc_w 'bonusXP' 
L33:    invokevirtual Method org/json/JSONObject getJSONObject (Ljava/lang/String;)Lorg/json/JSONObject; 
L36:    putstatic Field com/fs/starfarer/settings/StarfarerSettings 'oØ0000' Lorg/json/JSONObject; 
L39:    ldc_w 'defaultFont' 
L42:    invokestatic Method com/fs/starfarer/settings/StarfarerSettings while (Ljava/lang/String;)Ljava/lang/String; 
L45:    putstatic Field com/fs/starfarer/settings/StarfarerSettings 'float.new' Ljava/lang/String; 
L48:    ldc_w 'com.fs.starfarer.settings.osx' 
L51:    invokestatic Method java/lang/System getProperty (Ljava/lang/String;)Ljava/lang/String; 
L54:    ifnull L61 
L57:    iconst_1 
L58:    goto L62 

        .stack same 
L61:    iconst_0 

        .stack stack_1 Integer 
L62:    putstatic Field com/fs/starfarer/settings/StarfarerSettings 'null.class' Z 
L65:    ldc_w 'com.fs.starfarer.settings.linux' 
L68:    invokestatic Method java/lang/System getProperty (Ljava/lang/String;)Ljava/lang/String; 
L71:    ifnull L78 
L74:    iconst_1 
L75:    goto L79 

        .stack same 
L78:    iconst_0 

        .stack stack_1 Integer 
L79:    putstatic Field com/fs/starfarer/settings/StarfarerSettings 'OÕ0000' Z 
L82:    ldc_w 'suppliesPerMarinePerDay' 
L85:    invokestatic Method com/fs/starfarer/settings/StarfarerSettings 'ö00000' (Ljava/lang/String;)F 
L88:    putstatic Field com/fs/starfarer/settings/StarfarerSettings 'ÖÓ0000' F 
L91:    ldc_w 'minFighterReplacementRate' 
L94:    invokestatic Method com/fs/starfarer/settings/StarfarerSettings 'ö00000' (Ljava/lang/String;)F 
L97:    putstatic Field com/fs/starfarer/settings/StarfarerSettings 'ÔØ0000' F 
L100:   ldc_w 'renderDHullOverlay' 
L103:   invokestatic Method com/fs/starfarer/settings/StarfarerSettings class (Ljava/lang/String;)Z 
L106:   putstatic Field com/fs/starfarer/settings/StarfarerSettings 'class.class' Z 
L109:   ldc_w 'suppliesPerCrewPerDay' 
L112:   invokestatic Method com/fs/starfarer/settings/StarfarerSettings 'ö00000' (Ljava/lang/String;)F 
L115:   putstatic Field com/fs/starfarer/settings/StarfarerSettings 'ÓO0000' F 
L118:   ldc_w 'suppliesPerCargoUnitOverCapacity' 
L121:   invokestatic Method com/fs/starfarer/settings/StarfarerSettings 'ö00000' (Ljava/lang/String;)F 
L124:   putstatic Field com/fs/starfarer/settings/StarfarerSettings 'õÕ0000' F 
L127:   ldc_w 'suppliesPerFuelUnitOverCapacity' 
L130:   invokestatic Method com/fs/starfarer/settings/StarfarerSettings 'ö00000' (Ljava/lang/String;)F 
L133:   putstatic Field com/fs/starfarer/settings/StarfarerSettings 'ÖØ0000' F 
L136:   ldc_w 'suppliesPerPersonnelUnitOverCapacity' 
L139:   invokestatic Method com/fs/starfarer/settings/StarfarerSettings 'ö00000' (Ljava/lang/String;)F 
L142:   putstatic Field com/fs/starfarer/settings/StarfarerSettings 'class.super' F 
L145:   ldc_w 'supplyConsumptionMothballedMult' 
L148:   invokestatic Method com/fs/starfarer/settings/StarfarerSettings 'ö00000' (Ljava/lang/String;)F 
L151:   putstatic Field com/fs/starfarer/settings/StarfarerSettings 'ØÓ0000' F 
L154:   ldc_w 'uiFadeSpeedMult' 
L157:   invokestatic Method com/fs/starfarer/settings/StarfarerSettings 'ö00000' (Ljava/lang/String;)F 
L160:   putstatic Field com/fs/starfarer/settings/StarfarerSettings 'float.Object' F 
L163:   ldc_w 'minArmorFraction' 
L166:   invokestatic Method com/fs/starfarer/settings/StarfarerSettings 'ö00000' (Ljava/lang/String;)F 
L169:   putstatic Field com/fs/starfarer/settings/StarfarerSettings 'ÔÒ0000' F 
L172:   ldc_w 'baseTravelSpeed' 
L175:   invokestatic Method com/fs/starfarer/settings/StarfarerSettings 'ö00000' (Ljava/lang/String;)F 
L178:   putstatic Field com/fs/starfarer/settings/StarfarerSettings 'null.String' F 
L181:   ldc_w 'speedPerBurnLevel' 
L184:   invokestatic Method com/fs/starfarer/settings/StarfarerSettings 'ö00000' (Ljava/lang/String;)F 
L187:   putstatic Field com/fs/starfarer/settings/StarfarerSettings 'ÔÖ0000' F 
L190:   ldc_w 'unitsPerLightYear' 
L193:   invokestatic Method com/fs/starfarer/settings/StarfarerSettings 'ö00000' (Ljava/lang/String;)F 
L196:   putstatic Field com/fs/starfarer/settings/StarfarerSettings 'õÖ0000' F 
L199:   ldc_w 'maxArmorDamageReduction' 
L202:   invokestatic Method com/fs/starfarer/settings/StarfarerSettings 'ö00000' (Ljava/lang/String;)F 
L205:   putstatic Field com/fs/starfarer/settings/StarfarerSettings 'new.class' F 
L208:   ldc_w 'dpsToHitStrengthMult' 
L211:   invokestatic Method com/fs/starfarer/settings/StarfarerSettings 'ö00000' (Ljava/lang/String;)F 
L214:   putstatic Field com/fs/starfarer/settings/StarfarerSettings 'Øo0000' F 
L217:   ldc_w 'baseRepairRateFrigate' 
L220:   invokestatic Method com/fs/starfarer/settings/StarfarerSettings 'ö00000' (Ljava/lang/String;)F 
L223:   putstatic Field com/fs/starfarer/settings/StarfarerSettings null F 
L226:   ldc_w 'baseRepairRateDestroyer' 
L229:   invokestatic Method com/fs/starfarer/settings/StarfarerSettings 'ö00000' (Ljava/lang/String;)F 
L232:   putstatic Field com/fs/starfarer/settings/StarfarerSettings 'oÖ0000' F 
L235:   ldc_w 'baseRepairRateCruiser' 
L238:   invokestatic Method com/fs/starfarer/settings/StarfarerSettings 'ö00000' (Ljava/lang/String;)F 
L241:   putstatic Field com/fs/starfarer/settings/StarfarerSettings 'ØO0000' F 
L244:   ldc_w 'baseRepairRateCapital' 
L247:   invokestatic Method com/fs/starfarer/settings/StarfarerSettings 'ö00000' (Ljava/lang/String;)F 
L250:   putstatic Field com/fs/starfarer/settings/StarfarerSettings Oo0000 F 
L253:   ldc_w 'sensorRangeBase' 
L256:   invokestatic Method com/fs/starfarer/settings/StarfarerSettings 'ö00000' (Ljava/lang/String;)F 
L259:   putstatic Field com/fs/starfarer/settings/StarfarerSettings 'ÓÔ0000' F 
L262:   ldc_w 'baseSensorFrigate' 
L265:   invokestatic Method com/fs/starfarer/settings/StarfarerSettings 'ö00000' (Ljava/lang/String;)F 
L268:   putstatic Field com/fs/starfarer/settings/StarfarerSettings 'ÖO0000' F 
L271:   ldc_w 'baseSensorDestroyer' 
L274:   invokestatic Method com/fs/starfarer/settings/StarfarerSettings 'ö00000' (Ljava/lang/String;)F 
L277:   putstatic Field com/fs/starfarer/settings/StarfarerSettings 'interface.Object' F 
L280:   ldc_w 'baseSensorCruiser' 
L283:   invokestatic Method com/fs/starfarer/settings/StarfarerSettings 'ö00000' (Ljava/lang/String;)F 
L286:   putstatic Field com/fs/starfarer/settings/StarfarerSettings 'float.super' F 
L289:   ldc_w 'baseSensorCapital' 
L292:   invokestatic Method com/fs/starfarer/settings/StarfarerSettings 'ö00000' (Ljava/lang/String;)F 
L295:   putstatic Field com/fs/starfarer/settings/StarfarerSettings 'while.super' F 
L298:   ldc_w 'maxSensorShips' 
L301:   invokestatic Method com/fs/starfarer/settings/StarfarerSettings 'ö00000' (Ljava/lang/String;)F 
L304:   putstatic Field com/fs/starfarer/settings/StarfarerSettings 'class.return' F 
L307:   ldc_w 'maxShipsInFleet' 
L310:   invokestatic Method com/fs/starfarer/settings/StarfarerSettings 'ö00000' (Ljava/lang/String;)F 
L313:   putstatic Field com/fs/starfarer/settings/StarfarerSettings 'new.new' F 
L316:   ldc_w 'suppliesPerShipOverMaxInFleet' 
L319:   invokestatic Method com/fs/starfarer/settings/StarfarerSettings 'ö00000' (Ljava/lang/String;)F 
L322:   putstatic Field com/fs/starfarer/settings/StarfarerSettings 'interface.String' F 
L325:   ldc_w 'sensorRangeMax' 
L328:   invokestatic Method com/fs/starfarer/settings/StarfarerSettings 'ö00000' (Ljava/lang/String;)F 
L331:   putstatic Field com/fs/starfarer/settings/StarfarerSettings 'float.class' F 
L334:   ldc_w 'sensorRangeMaxHyper' 
L337:   invokestatic Method com/fs/starfarer/settings/StarfarerSettings 'ö00000' (Ljava/lang/String;)F 
L340:   putstatic Field com/fs/starfarer/settings/StarfarerSettings 'float.String' F 
L343:   ldc_w 'detectionRangeTransponderMult' 
L346:   invokestatic Method com/fs/starfarer/settings/StarfarerSettings 'ö00000' (Ljava/lang/String;)F 
L349:   putstatic Field com/fs/starfarer/settings/StarfarerSettings 'Óô0000' F 
L352:   ldc_w 'detectionRangeDetailsMult' 
L355:   invokestatic Method com/fs/starfarer/settings/StarfarerSettings 'ö00000' (Ljava/lang/String;)F 
L358:   putstatic Field com/fs/starfarer/settings/StarfarerSettings 'interface.new' F 
L361:   ldc_w 'detectionRangeDetailsAlwaysMult' 
L364:   invokestatic Method com/fs/starfarer/settings/StarfarerSettings 'ö00000' (Ljava/lang/String;)F 
L367:   putstatic Field com/fs/starfarer/settings/StarfarerSettings 'class.Object' F 
L370:   ldc_w 'detectionRangeDetailsAlwaysNonFleet' 
L373:   invokestatic Method com/fs/starfarer/settings/StarfarerSettings 'ö00000' (Ljava/lang/String;)F 
L376:   putstatic Field com/fs/starfarer/settings/StarfarerSettings OO0000 F 
L379:   ldc_w 'detectionRangeDetailsAlwaysMin' 
L382:   invokestatic Method com/fs/starfarer/settings/StarfarerSettings 'ö00000' (Ljava/lang/String;)F 
L385:   putstatic Field com/fs/starfarer/settings/StarfarerSettings 'ÓÓ0000' F 
L388:   ldc_w 'baseFleetSelectionRadius' 
L391:   invokestatic Method com/fs/starfarer/settings/StarfarerSettings 'ö00000' (Ljava/lang/String;)F 
L394:   putstatic Field com/fs/starfarer/settings/StarfarerSettings 'new.Object' F 
L397:   ldc_w 'fleetSelectionRadiusPerUnitSize' 
L400:   invokestatic Method com/fs/starfarer/settings/StarfarerSettings 'ö00000' (Ljava/lang/String;)F 
L403:   putstatic Field com/fs/starfarer/settings/StarfarerSettings 'ØØ0000' F 
L406:   ldc_w 'maxFleetSelectionRadius' 
L409:   invokestatic Method com/fs/starfarer/settings/StarfarerSettings 'ö00000' (Ljava/lang/String;)F 
L412:   putstatic Field com/fs/starfarer/settings/StarfarerSettings 'OÓ0000' F 
L415:   ldc_w 'minVentTimeForWeaponReload' 
L418:   invokestatic Method com/fs/starfarer/settings/StarfarerSettings 'ö00000' (Ljava/lang/String;)F 
L421:   putstatic Field com/fs/starfarer/settings/StarfarerSettings 'ÔÔ0000' F 
L424:   ldc_w 'easyPlayerDamageDealtMult' 
L427:   invokestatic Method com/fs/starfarer/settings/StarfarerSettings 'ö00000' (Ljava/lang/String;)F 
L430:   putstatic Field com/fs/starfarer/settings/StarfarerSettings 'while.new' F 
L433:   ldc_w 'easyPlayerDamageTakenMult' 
L436:   invokestatic Method com/fs/starfarer/settings/StarfarerSettings 'ö00000' (Ljava/lang/String;)F 
L439:   putstatic Field com/fs/starfarer/settings/StarfarerSettings 'class.new' F 
L442:   ldc_w 'easySensorBonus' 
L445:   invokestatic Method com/fs/starfarer/settings/StarfarerSettings 'ö00000' (Ljava/lang/String;)F 
L448:   putstatic Field com/fs/starfarer/settings/StarfarerSettings 'öÕ0000' F 
L451:   ldc_w 'defaultBattleSize' 
L454:   invokestatic Method com/fs/starfarer/settings/StarfarerSettings 'ö00000' (Ljava/lang/String;)F 
L457:   f2i 
L458:   putstatic Field com/fs/starfarer/settings/StarfarerSettings 'interface' I 
L461:   getstatic Field com/fs/starfarer/settings/StarfarerSettings 'õô0000' Ljava/util/Map; 
L464:   getstatic Field com/fs/starfarer/api/combat/ShipAPI$HullSize FIGHTER Lcom/fs/starfarer/api/combat/ShipAPI$HullSize; 
L467:   ldc_w 'nebulaSpeedFighter' 
L470:   invokestatic Method com/fs/starfarer/settings/StarfarerSettings 'ö00000' (Ljava/lang/String;)F 
L473:   invokestatic Method java/lang/Float valueOf (F)Ljava/lang/Float; 
L476:   invokeinterface InterfaceMethod java/util/Map put (Ljava/lang/Object;Ljava/lang/Object;)Ljava/lang/Object; 3 
L481:   pop 
L482:   getstatic Field com/fs/starfarer/settings/StarfarerSettings 'õô0000' Ljava/util/Map; 
L485:   getstatic Field com/fs/starfarer/api/combat/ShipAPI$HullSize FRIGATE Lcom/fs/starfarer/api/combat/ShipAPI$HullSize; 
L488:   ldc_w 'nebulaSpeedFrigate' 
L491:   invokestatic Method com/fs/starfarer/settings/StarfarerSettings 'ö00000' (Ljava/lang/String;)F 
L494:   invokestatic Method java/lang/Float valueOf (F)Ljava/lang/Float; 
L497:   invokeinterface InterfaceMethod java/util/Map put (Ljava/lang/Object;Ljava/lang/Object;)Ljava/lang/Object; 3 
L502:   pop 
L503:   getstatic Field com/fs/starfarer/settings/StarfarerSettings 'õô0000' Ljava/util/Map; 
L506:   getstatic Field com/fs/starfarer/api/combat/ShipAPI$HullSize DESTROYER Lcom/fs/starfarer/api/combat/ShipAPI$HullSize; 
L509:   ldc_w 'nebulaSpeedDestroyer' 
L512:   invokestatic Method com/fs/starfarer/settings/StarfarerSettings 'ö00000' (Ljava/lang/String;)F 
L515:   invokestatic Method java/lang/Float valueOf (F)Ljava/lang/Float; 
L518:   invokeinterface InterfaceMethod java/util/Map put (Ljava/lang/Object;Ljava/lang/Object;)Ljava/lang/Object; 3 
L523:   pop 
L524:   getstatic Field com/fs/starfarer/settings/StarfarerSettings 'õô0000' Ljava/util/Map; 
L527:   getstatic Field com/fs/starfarer/api/combat/ShipAPI$HullSize CRUISER Lcom/fs/starfarer/api/combat/ShipAPI$HullSize; 
L530:   ldc_w 'nebulaSpeedCruiser' 
L533:   invokestatic Method com/fs/starfarer/settings/StarfarerSettings 'ö00000' (Ljava/lang/String;)F 
L536:   invokestatic Method java/lang/Float valueOf (F)Ljava/lang/Float; 
L539:   invokeinterface InterfaceMethod java/util/Map put (Ljava/lang/Object;Ljava/lang/Object;)Ljava/lang/Object; 3 
L544:   pop 
L545:   getstatic Field com/fs/starfarer/settings/StarfarerSettings 'õô0000' Ljava/util/Map; 
L548:   getstatic Field com/fs/starfarer/api/combat/ShipAPI$HullSize CAPITAL_SHIP Lcom/fs/starfarer/api/combat/ShipAPI$HullSize; 
L551:   ldc_w 'nebulaSpeedCapital' 
L554:   invokestatic Method com/fs/starfarer/settings/StarfarerSettings 'ö00000' (Ljava/lang/String;)F 
L557:   invokestatic Method java/lang/Float valueOf (F)Ljava/lang/Float; 
L560:   invokeinterface InterfaceMethod java/util/Map put (Ljava/lang/Object;Ljava/lang/Object;)Ljava/lang/Object; 3 
L565:   pop 
L566:   ldc_w 'autosaveEnabledByDefault' 
L569:   invokestatic Method com/fs/starfarer/settings/StarfarerSettings class (Ljava/lang/String;)Z 
L572:   putstatic Field com/fs/starfarer/settings/StarfarerSettings 'öÒ0000' Z 
L575:   ldc_w 'autosaveDefaultIntervalMinutes' 
L578:   invokestatic Method com/fs/starfarer/settings/StarfarerSettings 'ö00000' (Ljava/lang/String;)F 
L581:   putstatic Field com/fs/starfarer/settings/StarfarerSettings 'Ó00000' F 
L584:   invokestatic Method com/fs/starfarer/settings/StarfarerSettings 'öÕ0000' ()V 
L587:   invokestatic Method com/fs/starfarer/O0OO o00000 ()V 
L590:   invokestatic Method com/fs/starfarer/launcher/ooOO 'Ó00000' ()Lcom/fs/starfarer/launcher/ooOO; 
L593:   invokevirtual Method com/fs/starfarer/launcher/ooOO 'class.super' ()V 
L596:   return 
L597:   
    .end code 
.end method 

.method public static 'ÔÖ0000' : ()Z 
    .code stack 1 locals 0 
L0:     getstatic Field com/fs/starfarer/settings/StarfarerSettings 'class.class' Z 
L3:     ireturn 
L4:     
    .end code 
.end method 

.method public static 'ÓÔ0000' : ()F 
    .code stack 1 locals 0 
L0:     getstatic Field com/fs/starfarer/settings/StarfarerSettings 'while.new' F 
L3:     freturn 
L4:     
    .end code 
.end method 

.method public static 'õÒ0000' : ()F 
    .code stack 1 locals 0 
L0:     getstatic Field com/fs/starfarer/settings/StarfarerSettings 'class.new' F 
L3:     freturn 
L4:     
    .end code 
.end method 

.method public static 'öÓ0000' : ()F 
    .code stack 1 locals 0 
L0:     getstatic Field com/fs/starfarer/settings/StarfarerSettings 'öÕ0000' F 
L3:     freturn 
L4:     
    .end code 
.end method 

.method public static 'Ô00000' : (F)V 
    .code stack 1 locals 1 
L0:     fload_0 
L1:     putstatic Field com/fs/starfarer/settings/StarfarerSettings 'öÕ0000' F 
L4:     return 
L5:     
    .end code 
.end method 

.method public static 'õO0000' : ()F 
    .code stack 1 locals 0 
L0:     getstatic Field com/fs/starfarer/settings/StarfarerSettings 'new.Object' F 
L3:     freturn 
L4:     
    .end code 
.end method 

.method public static 'ÔO0000' : ()F 
    .code stack 1 locals 0 
L0:     getstatic Field com/fs/starfarer/settings/StarfarerSettings 'ØØ0000' F 
L3:     freturn 
L4:     
    .end code 
.end method 

.method public static 'class.String' : ()F 
    .code stack 1 locals 0 
L0:     getstatic Field com/fs/starfarer/settings/StarfarerSettings 'OÓ0000' F 
L3:     freturn 
L4:     
    .end code 
.end method 

.method public static 'interface.Object' : ()F 
    .code stack 1 locals 0 
L0:     getstatic Field com/fs/starfarer/settings/StarfarerSettings 'ÔÔ0000' F 
L3:     freturn 
L4:     
    .end code 
.end method 

.method public static o00000 : (Lcom/fs/starfarer/api/combat/ShipAPI$HullSize;)F 
    .code stack 2 locals 1 
L0:     getstatic Field com/fs/starfarer/settings/StarfarerSettings 'õô0000' Ljava/util/Map; 
L3:     aload_0 
L4:     invokeinterface InterfaceMethod java/util/Map containsKey (Ljava/lang/Object;)Z 2 
L9:     ifeq L28 
L12:    getstatic Field com/fs/starfarer/settings/StarfarerSettings 'õô0000' Ljava/util/Map; 
L15:    aload_0 
L16:    invokeinterface InterfaceMethod java/util/Map get (Ljava/lang/Object;)Ljava/lang/Object; 2 
L21:    checkcast java/lang/Float 
L24:    invokevirtual Method java/lang/Float floatValue ()F 
L27:    freturn 

        .stack same 
L28:    fconst_1 
L29:    freturn 
L30:    
    .end code 
.end method 

.method public static 'ÖÓ0000' : ()F 
    .code stack 1 locals 0 
L0:     getstatic Field com/fs/starfarer/settings/StarfarerSettings 'ÓÔ0000' F 
L3:     freturn 
L4:     
    .end code 
.end method 

.method public static 'õo0000' : ()F 
    .code stack 1 locals 0 
L0:     getstatic Field com/fs/starfarer/settings/StarfarerSettings 'ÖO0000' F 
L3:     freturn 
L4:     
    .end code 
.end method 

.method public static 'ÔÕ0000' : ()F 
    .code stack 1 locals 0 
L0:     getstatic Field com/fs/starfarer/settings/StarfarerSettings 'interface.Object' F 
L3:     freturn 
L4:     
    .end code 
.end method 

.method public static 'Ôo0000' : ()F 
    .code stack 1 locals 0 
L0:     getstatic Field com/fs/starfarer/settings/StarfarerSettings 'float.super' F 
L3:     freturn 
L4:     
    .end code 
.end method 

.method public static 'ØÖ0000' : ()F 
    .code stack 1 locals 0 
L0:     getstatic Field com/fs/starfarer/settings/StarfarerSettings 'class.return' F 
L3:     freturn 
L4:     
    .end code 
.end method 

.method public static 'ÓÒ0000' : ()F 
    .code stack 1 locals 0 
L0:     getstatic Field com/fs/starfarer/settings/StarfarerSettings 'while.super' F 
L3:     freturn 
L4:     
    .end code 
.end method 

.method public static o00000 : (Lcom/fs/starfarer/api/campaign/LocationAPI;)F 
    .code stack 1 locals 1 
L0:     aload_0 
L1:     ifnull L17 
L4:     aload_0 
L5:     invokeinterface InterfaceMethod com/fs/starfarer/api/campaign/LocationAPI isHyperspace ()Z 1 
L10:    ifeq L17 
L13:    getstatic Field com/fs/starfarer/settings/StarfarerSettings 'float.String' F 
L16:    freturn 

        .stack same 
L17:    getstatic Field com/fs/starfarer/settings/StarfarerSettings 'float.class' F 
L20:    freturn 
L21:    
    .end code 
.end method 

.method public static class : ()F 
    .code stack 1 locals 0 
L0:     getstatic Field com/fs/starfarer/settings/StarfarerSettings 'float.class' F 
L3:     freturn 
L4:     
    .end code 
.end method 

.method public static 'ÖÔ0000' : ()F 
    .code stack 1 locals 0 
L0:     getstatic Field com/fs/starfarer/settings/StarfarerSettings 'float.String' F 
L3:     freturn 
L4:     
    .end code 
.end method 

.method public static 'Ø00000' : ()F 
    .code stack 1 locals 0 
L0:     getstatic Field com/fs/starfarer/settings/StarfarerSettings 'Óô0000' F 
L3:     freturn 
L4:     
    .end code 
.end method 

.method public static 'new.class' : ()F 
    .code stack 1 locals 0 
L0:     getstatic Field com/fs/starfarer/settings/StarfarerSettings 'interface.new' F 
L3:     freturn 
L4:     
    .end code 
.end method 

.method public static 'interface' : ()F 
    .code stack 1 locals 0 
L0:     getstatic Field com/fs/starfarer/settings/StarfarerSettings 'class.Object' F 
L3:     freturn 
L4:     
    .end code 
.end method 

.method public static 'OÕ0000' : ()F 
    .code stack 1 locals 0 
L0:     getstatic Field com/fs/starfarer/settings/StarfarerSettings OO0000 F 
L3:     freturn 
L4:     
    .end code 
.end method 

.method public static 'null.super' : ()F 
    .code stack 1 locals 0 
L0:     getstatic Field com/fs/starfarer/settings/StarfarerSettings 'ÓÓ0000' F 
L3:     freturn 
L4:     
    .end code 
.end method 

.method public static new : (Lcom/fs/starfarer/api/combat/ShipAPI$HullSize;)F 
    .code stack 2 locals 1 
L0:     invokestatic Method com/fs/starfarer/settings/StarfarerSettings 'ØÔ0000' ()[I 
L3:     aload_0 
L4:     invokevirtual Method com/fs/starfarer/api/combat/ShipAPI$HullSize ordinal ()I 
L7:     iaload 
L8:     tableswitch 1 
            L60 
            L60 
            L60 
            L56 
            L52 
            L48 
            default : L64 


        .stack same 
L48:    getstatic Field com/fs/starfarer/settings/StarfarerSettings Oo0000 F 
L51:    freturn 

        .stack same 
L52:    getstatic Field com/fs/starfarer/settings/StarfarerSettings 'ØO0000' F 
L55:    freturn 

        .stack same 
L56:    getstatic Field com/fs/starfarer/settings/StarfarerSettings 'oÖ0000' F 
L59:    freturn 

        .stack same 
L60:    getstatic Field com/fs/starfarer/settings/StarfarerSettings null F 
L63:    freturn 

        .stack same 
L64:    getstatic Field com/fs/starfarer/settings/StarfarerSettings null F 
L67:    freturn 
L68:    
    .end code 
.end method 

.method public static 'õÔ0000' : ()F 
    .code stack 1 locals 0 
L0:     getstatic Field com/fs/starfarer/settings/StarfarerSettings null F 
L3:     freturn 
L4:     
    .end code 
.end method 

.method public static 'Öo0000' : ()F 
    .code stack 1 locals 0 
L0:     getstatic Field com/fs/starfarer/settings/StarfarerSettings 'oÖ0000' F 
L3:     freturn 
L4:     
    .end code 
.end method 

.method public static 'float.Object' : ()F 
    .code stack 1 locals 0 
L0:     getstatic Field com/fs/starfarer/settings/StarfarerSettings 'ØO0000' F 
L3:     freturn 
L4:     
    .end code 
.end method 

.method public static 'oÔ0000' : ()F 
    .code stack 1 locals 0 
L0:     getstatic Field com/fs/starfarer/settings/StarfarerSettings Oo0000 F 
L3:     freturn 
L4:     
    .end code 
.end method 

.method public static 'while.Object' : ()F 
    .code stack 1 locals 0 
L0:     getstatic Field com/fs/starfarer/settings/StarfarerSettings 'new.class' F 
L3:     freturn 
L4:     
    .end code 
.end method 

.method public static 'õÕ0000' : ()F 
    .code stack 1 locals 0 
L0:     getstatic Field com/fs/starfarer/settings/StarfarerSettings 'interface.String' F 
L3:     freturn 
L4:     
    .end code 
.end method 

.method public static 'OÒ0000' : ()I 
    .code stack 1 locals 0 
L0:     getstatic Field com/fs/starfarer/settings/StarfarerSettings 'new.new' F 
L3:     f2i 
L4:     ireturn 
L5:     
    .end code 
.end method 

.method public static 'new.Object' : ()I 
    .code stack 1 locals 0 
L0:     getstatic Field com/fs/starfarer/settings/StarfarerSettings 'float.class' F 
L3:     f2i 
L4:     ireturn 
L5:     
    .end code 
.end method 

.method public static 'öO0000' : ()I 
    .code stack 1 locals 0 
L0:     getstatic Field com/fs/starfarer/settings/StarfarerSettings 'float.String' F 
L3:     f2i 
L4:     ireturn 
L5:     
    .end code 
.end method 

.method public static 'õÓ0000' : ()F 
    .code stack 1 locals 0 
L0:     getstatic Field com/fs/starfarer/settings/StarfarerSettings 'Øo0000' F 
L3:     freturn 
L4:     
    .end code 
.end method 

.method public static 'Ó00000' : ()F 
    .code stack 1 locals 0 
L0:     getstatic Field com/fs/starfarer/settings/StarfarerSettings 'õÖ0000' F 
L3:     freturn 
L4:     
    .end code 
.end method 

.method public static 'Oô0000' : ()F 
    .code stack 1 locals 0 
L0:     getstatic Field com/fs/starfarer/settings/StarfarerSettings 'null.String' F 
L3:     freturn 
L4:     
    .end code 
.end method 

.method public static 'ÓØ0000' : ()F 
    .code stack 1 locals 0 
L0:     getstatic Field com/fs/starfarer/settings/StarfarerSettings 'ÔÒ0000' F 
L3:     freturn 
L4:     
    .end code 
.end method 

.method public static 'new.new' : ()F 
    .code stack 1 locals 0 
L0:     getstatic Field com/fs/starfarer/settings/StarfarerSettings 'ÔÖ0000' F 
L3:     freturn 
L4:     
    .end code 
.end method 

.method public static 'Óô0000' : ()F 
    .code stack 1 locals 0 
L0:     getstatic Field com/fs/starfarer/settings/StarfarerSettings 'ØÓ0000' F 
L3:     freturn 
L4:     
    .end code 
.end method 

.method public static 'ØÒ0000' : ()F 
    .code stack 1 locals 0 
L0:     getstatic Field com/fs/starfarer/settings/StarfarerSettings 'õÕ0000' F 
L3:     freturn 
L4:     
    .end code 
.end method 

.method public static 'ÖØ0000' : ()F 
    .code stack 1 locals 0 
L0:     getstatic Field com/fs/starfarer/settings/StarfarerSettings 'ÖØ0000' F 
L3:     freturn 
L4:     
    .end code 
.end method 

.method public static 'ÔÓ0000' : ()F 
    .code stack 1 locals 0 
L0:     getstatic Field com/fs/starfarer/settings/StarfarerSettings 'class.super' F 
L3:     freturn 
L4:     
    .end code 
.end method 

.method public static 'öo0000' : ()F 
    .code stack 1 locals 0 
L0:     getstatic Field com/fs/starfarer/settings/StarfarerSettings 'ÓO0000' F 
L3:     freturn 
L4:     
    .end code 
.end method 

.method public static 'null.class' : ()F 
    .code stack 1 locals 0 
L0:     getstatic Field com/fs/starfarer/settings/StarfarerSettings 'ÖÓ0000' F 
L3:     freturn 
L4:     
    .end code 
.end method 

.method public static oo0000 : ()F 
    .code stack 1 locals 0 
L0:     getstatic Field com/fs/starfarer/settings/StarfarerSettings 'ÔØ0000' F 
L3:     freturn 
L4:     
    .end code 
.end method 

.method public static 'Ø00000' : (Ljava/lang/String;)Ljava/lang/String; 
    .code stack 7 locals 3 
        .catch org/json/JSONException from L0 to L47 using L48 
L0:     getstatic Field com/fs/starfarer/settings/StarfarerSettings 'õØ0000' Lorg/json/JSONObject; 
L3:     ldc_w 'plugins' 
L6:     invokevirtual Method org/json/JSONObject getJSONObject (Ljava/lang/String;)Lorg/json/JSONObject; 
L9:     astore_1 
L10:    aload_1 
L11:    aload_0 
L12:    invokevirtual Method org/json/JSONObject has (Ljava/lang/String;)Z 
L15:    ifne L40 
L18:    new java/lang/RuntimeException 
L21:    dup 
L22:    ldc_w 'Plugin [%s] from "plugins" not found' 
L25:    iconst_1 
L26:    anewarray java/lang/Object 
L29:    dup 
L30:    iconst_0 
L31:    aload_0 
L32:    aastore 
L33:    invokestatic Method java/lang/String format (Ljava/lang/String;[Ljava/lang/Object;)Ljava/lang/String; 
L36:    invokespecial Method java/lang/RuntimeException <init> (Ljava/lang/String;)V 
L39:    athrow 

        .stack append Object org/json/JSONObject 
L40:    aload_1 
L41:    aload_0 
L42:    invokevirtual Method org/json/JSONObject getString (Ljava/lang/String;)Ljava/lang/String; 
L45:    astore_2 
L46:    aload_2 
L47:    areturn 

        .stack full 
            locals Object java/lang/String 
            stack Object org/json/JSONException 
        .end stack 
L48:    astore_1 
L49:    aconst_null 
L50:    areturn 
L51:    
    .end code 
.end method 

.method public static 'float.String' : ()Lcom/fs/starfarer/api/combat/CombatReadinessPlugin; 
    .code stack 1 locals 0 
L0:     getstatic Field com/fs/starfarer/settings/StarfarerSettings oo0000 Lcom/fs/starfarer/api/combat/CombatReadinessPlugin; 
L3:     ifnonnull L18 
L6:     ldc_w 'combatReadinessPlugin' 
L9:     invokestatic Method com/fs/starfarer/settings/StarfarerSettings 'Ö00000' (Ljava/lang/String;)Ljava/lang/Object; 
L12:    checkcast com/fs/starfarer/api/combat/CombatReadinessPlugin 
L15:    putstatic Field com/fs/starfarer/settings/StarfarerSettings oo0000 Lcom/fs/starfarer/api/combat/CombatReadinessPlugin; 

        .stack same 
L18:    getstatic Field com/fs/starfarer/settings/StarfarerSettings oo0000 Lcom/fs/starfarer/api/combat/CombatReadinessPlugin; 
L21:    areturn 
L22:    
    .end code 
.end method 

.method public static 'Ö00000' : (Ljava/lang/String;)Ljava/lang/Object; 
    .code stack 3 locals 4 
L0:     getstatic Field com/fs/starfarer/settings/StarfarerSettings 'Ô00000' Ljava/util/Map; 
L3:     aload_0 
L4:     invokeinterface InterfaceMethod java/util/Map containsKey (Ljava/lang/Object;)Z 2 
L9:     ifeq L22 
L12:    getstatic Field com/fs/starfarer/settings/StarfarerSettings 'Ô00000' Ljava/util/Map; 
L15:    aload_0 
L16:    invokeinterface InterfaceMethod java/util/Map get (Ljava/lang/Object;)Ljava/lang/Object; 2 
L21:    areturn 

        .stack same 
L22:    aload_0 
L23:    invokestatic Method com/fs/starfarer/settings/StarfarerSettings 'Ø00000' (Ljava/lang/String;)Ljava/lang/String; 
L26:    astore_1 
        .catch java/lang/ClassNotFoundException from L27 to L53 using L54 
L27:    aload_1 
L28:    iconst_1 
L29:    invokestatic Method com/fs/starfarer/loading/scripts/ScriptStore 'Ø00000' ()Lorg/codehaus/janino/JavaSourceClassLoader; 
L32:    invokestatic Method java/lang/Class forName (Ljava/lang/String;ZLjava/lang/ClassLoader;)Ljava/lang/Class; 
L35:    astore_2 
L36:    aload_2 
L37:    invokestatic Method com/fs/starfarer/loading/scripts/ScriptStore o00000 (Ljava/lang/Class;)Ljava/lang/Object; 
L40:    astore_3 
L41:    getstatic Field com/fs/starfarer/settings/StarfarerSettings 'Ô00000' Ljava/util/Map; 
L44:    aload_0 
L45:    aload_3 
L46:    invokeinterface InterfaceMethod java/util/Map put (Ljava/lang/Object;Ljava/lang/Object;)Ljava/lang/Object; 3 
L51:    pop 
L52:    aload_3 
L53:    areturn 

        .stack full 
            locals Object java/lang/String Object java/lang/String 
            stack Object java/lang/ClassNotFoundException 
        .end stack 
L54:    astore_2 
L55:    aconst_null 
L56:    areturn 
L57:    
    .end code 
.end method 

.method public static 'ÓO0000' : (Ljava/lang/String;)Ljava/lang/Object; 
    .code stack 3 locals 3 
L0:     aload_0 
L1:     invokestatic Method com/fs/starfarer/settings/StarfarerSettings 'Ø00000' (Ljava/lang/String;)Ljava/lang/String; 
L4:     astore_1 
        .catch java/lang/ClassNotFoundException from L5 to L18 using L19 
L5:     aload_1 
L6:     iconst_1 
L7:     invokestatic Method com/fs/starfarer/loading/scripts/ScriptStore 'Ø00000' ()Lorg/codehaus/janino/JavaSourceClassLoader; 
L10:    invokestatic Method java/lang/Class forName (Ljava/lang/String;ZLjava/lang/ClassLoader;)Ljava/lang/Class; 
L13:    astore_2 
L14:    aload_2 
L15:    invokestatic Method com/fs/starfarer/loading/scripts/ScriptStore 'Ò00000' (Ljava/lang/Class;)Ljava/lang/Object; 
L18:    areturn 

        .stack full 
            locals Object java/lang/String Object java/lang/String 
            stack Object java/lang/ClassNotFoundException 
        .end stack 
L19:    astore_2 
L20:    aconst_null 
L21:    areturn 
L22:    
    .end code 
.end method 

.method public static 'OÖ0000' : ()Lorg/json/JSONObject; 
    .code stack 1 locals 0 
L0:     getstatic Field com/fs/starfarer/settings/StarfarerSettings 'õØ0000' Lorg/json/JSONObject; 
L3:     areturn 
L4:     
    .end code 
.end method 

.method public static 'ØO0000' : ()Z 
    .code stack 1 locals 0 
L0:     getstatic Field com/fs/starfarer/settings/StarfarerSettings 'null.return' Z 
L3:     ireturn 
L4:     
    .end code 
.end method 

.method public static null : (Z)V 
    .code stack 1 locals 1 
L0:     iload_0 
L1:     putstatic Field com/fs/starfarer/settings/StarfarerSettings 'null.return' Z 
L4:     return 
L5:     
    .end code 
.end method 

.method public static 'ÓÕ0000' : ()Z 
    .code stack 1 locals 0 
L0:     getstatic Field com/fs/starfarer/settings/StarfarerSettings while Z 
L3:     ireturn 
L4:     
    .end code 
.end method 

.method public static class : (Z)V 
    .code stack 1 locals 1 
L0:     iload_0 
L1:     putstatic Field com/fs/starfarer/settings/StarfarerSettings while Z 
L4:     return 
L5:     
    .end code 
.end method 

.method public static while : ()Z 
    .code stack 1 locals 0 
L0:     getstatic Field com/fs/starfarer/settings/StarfarerSettings 'Øô0000' Z 
L3:     ireturn 
L4:     
    .end code 
.end method 

.method public static new : (Z)V 
    .code stack 1 locals 1 
L0:     iload_0 
L1:     putstatic Field com/fs/starfarer/settings/StarfarerSettings 'Øô0000' Z 
L4:     return 
L5:     
    .end code 
.end method 

.method public static 'õÖ0000' : ()Z 
    .code stack 1 locals 0 
L0:     getstatic Field com/fs/starfarer/settings/StarfarerSettings 'ö00000' Z 
L3:     ireturn 
L4:     
    .end code 
.end method 

.method public static float : (Z)V 
    .code stack 1 locals 1 
L0:     iload_0 
L1:     putstatic Field com/fs/starfarer/settings/StarfarerSettings 'ö00000' Z 
L4:     return 
L5:     
    .end code 
.end method 

.method public static OO0000 : ()Z 
    .code stack 1 locals 0 
L0:     getstatic Field com/fs/starfarer/settings/StarfarerSettings 'null.class' Z 
L3:     ireturn 
L4:     
    .end code 
.end method 

.method public static 'öÖ0000' : ()Z 
    .code stack 1 locals 0 
L0:     getstatic Field com/fs/starfarer/settings/StarfarerSettings 'OÕ0000' Z 
L3:     ireturn 
L4:     
    .end code 
.end method 

.method public static 'ØÕ0000' : ()Z 
    .code stack 1 locals 0 
L0:     ldc_w 'launchDirect' 
L3:     invokestatic Method java/lang/System getProperty (Ljava/lang/String;)Ljava/lang/String; 
L6:     ifnull L11 
L9:     iconst_1 
L10:    ireturn 

        .stack same 
L11:    iconst_0 
L12:    ireturn 
L13:    
    .end code 
.end method 

.method public static 'ÖÒ0000' : ()Ljava/lang/String; 
    .code stack 1 locals 0 
L0:     ldc_w 'com.fs.starfarer.settings.paths.logs' 
L3:     invokestatic Method java/lang/System getProperty (Ljava/lang/String;)Ljava/lang/String; 
L6:     areturn 
L7:     
    .end code 
.end method 

.method public static 'oÓ0000' : ()Ljava/lang/String; 
    .code stack 1 locals 0 
L0:     ldc_w 'com.fs.starfarer.settings.paths.saves' 
L3:     invokestatic Method java/lang/System getProperty (Ljava/lang/String;)Ljava/lang/String; 
L6:     areturn 
L7:     
    .end code 
.end method 

.method public static 'OØ0000' : ()Ljava/lang/String; 
    .code stack 1 locals 0 
L0:     ldc_w 'com.fs.starfarer.settings.paths.screenshots' 
L3:     invokestatic Method java/lang/System getProperty (Ljava/lang/String;)Ljava/lang/String; 
L6:     areturn 
L7:     
    .end code 
.end method 

.method public static 'oô0000' : ()Ljava/lang/String; 
    .code stack 1 locals 0 
L0:     ldc_w 'com.fs.starfarer.settings.paths.mods' 
L3:     invokestatic Method java/lang/System getProperty (Ljava/lang/String;)Ljava/lang/String; 
L6:     areturn 
L7:     
    .end code 
.end method 

.method public static o00000 : (Lcom/fs/starfarer/loading/ResourceLoaderState;)V 
    .exceptions org/json/JSONException 
    .code stack 4 locals 14 
L0:     getstatic Field com/fs/starfarer/settings/StarfarerSettings 'õÓ0000' Lorg/json/JSONObject; 
L3:     invokestatic Method org/json/JSONObject getNames (Lorg/json/JSONObject;)[Ljava/lang/String; 
L6:     ifnull L257 
L9:     getstatic Field com/fs/starfarer/settings/StarfarerSettings 'õÓ0000' Lorg/json/JSONObject; 
L12:    invokestatic Method org/json/JSONObject getNames (Lorg/json/JSONObject;)[Ljava/lang/String; 
L15:    dup 
L16:    astore 4 
L18:    arraylength 
L19:    istore_3 
L20:    iconst_0 
L21:    istore_2 
L22:    goto L252 

        .stack full 
            locals Object com/fs/starfarer/loading/ResourceLoaderState Top Integer Integer Object [Ljava/lang/String; 
            stack 
        .end stack 
L25:    aload 4 
L27:    iload_2 
L28:    aaload 
L29:    astore_1 
L30:    getstatic Field com/fs/starfarer/settings/StarfarerSettings 'õÓ0000' Lorg/json/JSONObject; 
L33:    aload_1 
L34:    invokevirtual Method org/json/JSONObject getJSONObject (Ljava/lang/String;)Lorg/json/JSONObject; 
L37:    astore 5 
L39:    aload 5 
L41:    invokestatic Method org/json/JSONObject getNames (Lorg/json/JSONObject;)[Ljava/lang/String; 
L44:    ifnull L249 
L47:    aload 5 
L49:    invokestatic Method org/json/JSONObject getNames (Lorg/json/JSONObject;)[Ljava/lang/String; 
L52:    dup 
L53:    astore 9 
L55:    arraylength 
L56:    istore 8 
L58:    iconst_0 
L59:    istore 7 
L61:    goto L242 

        .stack full 
            locals Object com/fs/starfarer/loading/ResourceLoaderState Object java/lang/String Integer Integer Object [Ljava/lang/String; Object org/json/JSONObject Top Integer Integer Object [Ljava/lang/String; 
            stack 
        .end stack 
L64:    aload 9 
L66:    iload 7 
L68:    aaload 
L69:    astore 6 
L71:    new java/util/ArrayList 
L74:    dup 
L75:    invokespecial Method java/util/ArrayList <init> ()V 
L78:    astore 10 
L80:    aload 5 
L82:    aload 6 
L84:    invokevirtual Method org/json/JSONObject optJSONArray (Ljava/lang/String;)Lorg/json/JSONArray; 
L87:    astore 11 
L89:    aload 11 
L91:    ifnull L131 
L94:    iconst_0 
L95:    istore 12 
L97:    goto L118 

        .stack full 
            locals Object com/fs/starfarer/loading/ResourceLoaderState Object java/lang/String Integer Integer Object [Ljava/lang/String; Object org/json/JSONObject Object java/lang/String Integer Integer Object [Ljava/lang/String; Object java/util/List Object org/json/JSONArray Integer 
            stack 
        .end stack 
L100:   aload 10 
L102:   aload 11 
L104:   iload 12 
L106:   invokevirtual Method org/json/JSONArray getString (I)Ljava/lang/String; 
L109:   invokeinterface InterfaceMethod java/util/List add (Ljava/lang/Object;)Z 2 
L114:   pop 
L115:   iinc 12 1 

        .stack same 
L118:   iload 12 
L120:   aload 11 
L122:   invokevirtual Method org/json/JSONArray length ()I 
L125:   if_icmplt L100 
L128:   goto L146 

        .stack chop 1 
L131:   aload 10 
L133:   aload 5 
L135:   aload 6 
L137:   invokevirtual Method org/json/JSONObject getString (Ljava/lang/String;)Ljava/lang/String; 
L140:   invokeinterface InterfaceMethod java/util/List add (Ljava/lang/Object;)Z 2 
L145:   pop 

        .stack same 
L146:   aload 10 
L148:   invokeinterface InterfaceMethod java/util/List iterator ()Ljava/util/Iterator; 1 
L153:   astore 13 
L155:   goto L229 

        .stack full 
            locals Object com/fs/starfarer/loading/ResourceLoaderState Object java/lang/String Integer Integer Object [Ljava/lang/String; Object org/json/JSONObject Object java/lang/String Integer Integer Object [Ljava/lang/String; Object java/util/List Object org/json/JSONArray Top Object java/util/Iterator 
            stack 
        .end stack 
L158:   aload 13 
L160:   invokeinterface InterfaceMethod java/util/Iterator next ()Ljava/lang/Object; 1 
L165:   checkcast java/lang/String 
L168:   astore 12 
L170:   aload 12 
L172:   ldc_w 'backgrounds' 
L175:   invokevirtual Method java/lang/String contains (Ljava/lang/CharSequence;)Z 
L178:   ifeq L195 
L181:   aload_0 
L182:   getstatic Field com/fs/starfarer/loading/ResourceLoaderState$o 'Ò00000' Lcom/fs/starfarer/loading/ResourceLoaderState$o; 
L185:   aload 12 
L187:   bipush 20 
L189:   invokevirtual Method com/fs/starfarer/loading/ResourceLoaderState queueResource (Lcom/fs/starfarer/loading/ResourceLoaderState$o;Ljava/lang/String;I)V 
L192:   goto L229 

        .stack full 
            locals Object com/fs/starfarer/loading/ResourceLoaderState Object java/lang/String Integer Integer Object [Ljava/lang/String; Object org/json/JSONObject Object java/lang/String Integer Integer Object [Ljava/lang/String; Object java/util/List Object org/json/JSONArray Object java/lang/String Object java/util/Iterator 
            stack 
        .end stack 
L195:   aload 12 
L197:   ldc_w 'illustrations' 
L200:   invokevirtual Method java/lang/String contains (Ljava/lang/CharSequence;)Z 
L203:   ifeq L219 
L206:   aload_0 
L207:   getstatic Field com/fs/starfarer/loading/ResourceLoaderState$o 'Ò00000' Lcom/fs/starfarer/loading/ResourceLoaderState$o; 
L210:   aload 12 
L212:   iconst_5 
L213:   invokevirtual Method com/fs/starfarer/loading/ResourceLoaderState queueResource (Lcom/fs/starfarer/loading/ResourceLoaderState$o;Ljava/lang/String;I)V 
L216:   goto L229 

        .stack same 
L219:   aload_0 
L220:   getstatic Field com/fs/starfarer/loading/ResourceLoaderState$o 'Ò00000' Lcom/fs/starfarer/loading/ResourceLoaderState$o; 
L223:   aload 12 
L225:   iconst_1 
L226:   invokevirtual Method com/fs/starfarer/loading/ResourceLoaderState queueResource (Lcom/fs/starfarer/loading/ResourceLoaderState$o;Ljava/lang/String;I)V 

        .stack full 
            locals Object com/fs/starfarer/loading/ResourceLoaderState Object java/lang/String Integer Integer Object [Ljava/lang/String; Object org/json/JSONObject Object java/lang/String Integer Integer Object [Ljava/lang/String; Object java/util/List Object org/json/JSONArray Top Object java/util/Iterator 
            stack 
        .end stack 
L229:   aload 13 
L231:   invokeinterface InterfaceMethod java/util/Iterator hasNext ()Z 1 
L236:   ifne L158 
L239:   iinc 7 1 

        .stack full 
            locals Object com/fs/starfarer/loading/ResourceLoaderState Object java/lang/String Integer Integer Object [Ljava/lang/String; Object org/json/JSONObject Top Integer Integer Object [Ljava/lang/String; 
            stack 
        .end stack 
L242:   iload 7 
L244:   iload 8 
L246:   if_icmplt L64 

        .stack full 
            locals Object com/fs/starfarer/loading/ResourceLoaderState Top Integer Integer Object [Ljava/lang/String; 
            stack 
        .end stack 
L249:   iinc 2 1 

        .stack same 
L252:   iload_2 
L253:   iload_3 
L254:   if_icmplt L25 

        .stack full 
            locals Object com/fs/starfarer/loading/ResourceLoaderState 
            stack 
        .end stack 
L257:   return 
L258:   
    .end code 
.end method 

.method public static 'Ó00000' : (Ljava/lang/String;)Lorg/json/JSONObject; 
    .exceptions org/json/JSONException 
    .code stack 2 locals 1 
L0:     getstatic Field com/fs/starfarer/settings/StarfarerSettings 'õØ0000' Lorg/json/JSONObject; 
L3:     aload_0 
L4:     invokevirtual Method org/json/JSONObject getJSONObject (Ljava/lang/String;)Lorg/json/JSONObject; 
L7:     areturn 
L8:     
    .end code 
.end method 

.method public static 'Ô00000' : (Ljava/lang/String;)Lorg/json/JSONArray; 
    .exceptions org/json/JSONException 
    .code stack 2 locals 1 
L0:     getstatic Field com/fs/starfarer/settings/StarfarerSettings 'õØ0000' Lorg/json/JSONObject; 
L3:     aload_0 
L4:     invokevirtual Method org/json/JSONObject getJSONArray (Ljava/lang/String;)Lorg/json/JSONArray; 
L7:     areturn 
L8:     
    .end code 
.end method 

.method public static o00000 : (Ljava/lang/String;)F 
    .code stack 4 locals 1 
L0:     getstatic Field com/fs/starfarer/settings/StarfarerSettings 'oØ0000' Lorg/json/JSONObject; 
L3:     aload_0 
L4:     dconst_0 
L5:     invokevirtual Method org/json/JSONObject optDouble (Ljava/lang/String;D)D 
L8:     d2f 
L9:     freturn 
L10:    
    .end code 
.end method 

.method public static 'Ö00000' : (Ljava/lang/String;Ljava/lang/String;)Lcom/fs/graphics/Sprite; 
    .code stack 3 locals 2 
L0:     aload_0 
L1:     aload_1 
L2:     iconst_0 
L3:     invokestatic Method com/fs/starfarer/settings/StarfarerSettings o00000 (Ljava/lang/String;Ljava/lang/String;Z)Lcom/fs/graphics/Sprite; 
L6:     areturn 
L7:     
    .end code 
.end method 

.method public static o00000 : (Ljava/lang/String;Ljava/lang/String;Z)Lcom/fs/graphics/Sprite; 
    .code stack 7 locals 5 
        .catch org/json/JSONException from L0 to L62 using L63 
L0:     getstatic Field com/fs/starfarer/settings/StarfarerSettings 'õÓ0000' Lorg/json/JSONObject; 
L3:     aload_0 
L4:     invokevirtual Method org/json/JSONObject getJSONObject (Ljava/lang/String;)Lorg/json/JSONObject; 
L7:     astore_3 
L8:     aload_3 
L9:     aload_1 
L10:    invokevirtual Method org/json/JSONObject has (Ljava/lang/String;)Z 
L13:    ifne L46 
L16:    iload_2 
L17:    ifne L46 
L20:    new java/lang/RuntimeException 
L23:    dup 
L24:    ldc_w 'Texture [%s] from category [%s] not found' 
L27:    iconst_2 
L28:    anewarray java/lang/Object 
L31:    dup 
L32:    iconst_0 
L33:    aload_1 
L34:    aastore 
L35:    dup 
L36:    iconst_1 
L37:    aload_0 
L38:    aastore 
L39:    invokestatic Method java/lang/String format (Ljava/lang/String;[Ljava/lang/Object;)Ljava/lang/String; 
L42:    invokespecial Method java/lang/RuntimeException <init> (Ljava/lang/String;)V 
L45:    athrow 

        .stack append Object org/json/JSONObject 
L46:    aload_3 
L47:    aload_1 
L48:    invokevirtual Method org/json/JSONObject getString (Ljava/lang/String;)Ljava/lang/String; 
L51:    astore 4 
L53:    new com/fs/graphics/Sprite 
L56:    dup 
L57:    aload 4 
L59:    invokespecial Method com/fs/graphics/Sprite <init> (Ljava/lang/String;)V 
L62:    areturn 

        .stack full 
            locals Object java/lang/String Object java/lang/String Integer 
            stack Object org/json/JSONException 
        .end stack 
L63:    astore_3 
L64:    aconst_null 
L65:    areturn 
L66:    
    .end code 
.end method 

.method public static class : (Ljava/lang/String;Ljava/lang/String;)Z 
    .code stack 2 locals 3 
        .catch org/json/JSONException from L0 to L13 using L14 
L0:     getstatic Field com/fs/starfarer/settings/StarfarerSettings 'õÓ0000' Lorg/json/JSONObject; 
L3:     aload_0 
L4:     invokevirtual Method org/json/JSONObject getJSONObject (Ljava/lang/String;)Lorg/json/JSONObject; 
L7:     astore_2 
L8:     aload_2 
L9:     aload_1 
L10:    invokevirtual Method org/json/JSONObject has (Ljava/lang/String;)Z 
L13:    ireturn 

        .stack stack_1 Object org/json/JSONException 
L14:    astore_2 
L15:    iconst_0 
L16:    ireturn 
L17:    
    .end code 
.end method 

.method public static 'ÔO0000' : (Ljava/lang/String;)Ljava/util/List; 
    .signature (Ljava/lang/String;)Ljava/util/List<Ljava/lang/String;>; 
    .code stack 2 locals 4 
        .catch org/json/JSONException from L0 to L50 using L51 
L0:     getstatic Field com/fs/starfarer/settings/StarfarerSettings 'õÓ0000' Lorg/json/JSONObject; 
L3:     aload_0 
L4:     invokevirtual Method org/json/JSONObject getJSONObject (Ljava/lang/String;)Lorg/json/JSONObject; 
L7:     astore_1 
L8:     new java/util/ArrayList 
L11:    dup 
L12:    invokespecial Method java/util/ArrayList <init> ()V 
L15:    astore_2 
L16:    aload_1 
L17:    invokevirtual Method org/json/JSONObject keys ()Ljava/util/Iterator; 
L20:    astore_3 
L21:    goto L40 

        .stack append Object org/json/JSONObject Object java/util/List Object java/util/Iterator 
L24:    aload_2 
L25:    aload_3 
L26:    invokeinterface InterfaceMethod java/util/Iterator next ()Ljava/lang/Object; 1 
L31:    checkcast java/lang/String 
L34:    invokeinterface InterfaceMethod java/util/List add (Ljava/lang/Object;)Z 2 
L39:    pop 

        .stack same 
L40:    aload_3 
L41:    invokeinterface InterfaceMethod java/util/Iterator hasNext ()Z 1 
L46:    ifne L24 
L49:    aload_2 
L50:    areturn 

        .stack full 
            locals Object java/lang/String 
            stack Object org/json/JSONException 
        .end stack 
L51:    astore_1 
L52:    aconst_null 
L53:    areturn 
L54:    
    .end code 
.end method 

.method public static 'Ô00000' : (Ljava/lang/String;Ljava/lang/String;)Ljava/util/List; 
    .signature (Ljava/lang/String;Ljava/lang/String;)Ljava/util/List<Ljava/lang/String;>; 
    .code stack 3 locals 6 
        .catch org/json/JSONException from L0 to L57 using L58 
L0:     getstatic Field com/fs/starfarer/settings/StarfarerSettings 'õÓ0000' Lorg/json/JSONObject; 
L3:     aload_0 
L4:     invokevirtual Method org/json/JSONObject getJSONObject (Ljava/lang/String;)Lorg/json/JSONObject; 
L7:     astore_2 
L8:     aload_2 
L9:     aload_1 
L10:    invokevirtual Method org/json/JSONObject getJSONArray (Ljava/lang/String;)Lorg/json/JSONArray; 
L13:    astore_3 
L14:    new java/util/ArrayList 
L17:    dup 
L18:    invokespecial Method java/util/ArrayList <init> ()V 
L21:    astore 4 
L23:    iconst_0 
L24:    istore 5 
L26:    goto L46 

        .stack full 
            locals Object java/lang/String Object java/lang/String Object org/json/JSONObject Object org/json/JSONArray Object java/util/List Integer 
            stack 
        .end stack 
L29:    aload 4 
L31:    aload_3 
L32:    iload 5 
L34:    invokevirtual Method org/json/JSONArray getString (I)Ljava/lang/String; 
L37:    invokeinterface InterfaceMethod java/util/List add (Ljava/lang/Object;)Z 2 
L42:    pop 
L43:    iinc 5 1 

        .stack same 
L46:    iload 5 
L48:    aload_3 
L49:    invokevirtual Method org/json/JSONArray length ()I 
L52:    if_icmplt L29 
L55:    aload 4 
L57:    areturn 

        .stack full 
            locals Object java/lang/String Object java/lang/String 
            stack Object org/json/JSONException 
        .end stack 
L58:    astore_2 
L59:    aconst_null 
L60:    areturn 
L61:    
    .end code 
.end method 

.method public static new : (Ljava/lang/String;Ljava/lang/String;)Ljava/lang/String; 
    .code stack 7 locals 4 
        .catch org/json/JSONException from L0 to L49 using L50 
L0:     getstatic Field com/fs/starfarer/settings/StarfarerSettings 'õÓ0000' Lorg/json/JSONObject; 
L3:     aload_0 
L4:     invokevirtual Method org/json/JSONObject getJSONObject (Ljava/lang/String;)Lorg/json/JSONObject; 
L7:     astore_2 
L8:     aload_2 
L9:     aload_1 
L10:    invokevirtual Method org/json/JSONObject has (Ljava/lang/String;)Z 
L13:    ifne L42 
L16:    new java/lang/RuntimeException 
L19:    dup 
L20:    ldc_w 'Texture [%s] from category [%s] not found' 
L23:    iconst_2 
L24:    anewarray java/lang/Object 
L27:    dup 
L28:    iconst_0 
L29:    aload_1 
L30:    aastore 
L31:    dup 
L32:    iconst_1 
L33:    aload_0 
L34:    aastore 
L35:    invokestatic Method java/lang/String format (Ljava/lang/String;[Ljava/lang/Object;)Ljava/lang/String; 
L38:    invokespecial Method java/lang/RuntimeException <init> (Ljava/lang/String;)V 
L41:    athrow 

        .stack append Object org/json/JSONObject 
L42:    aload_2 
L43:    aload_1 
L44:    invokevirtual Method org/json/JSONObject getString (Ljava/lang/String;)Ljava/lang/String; 
L47:    astore_3 
L48:    aload_3 
L49:    areturn 

        .stack full 
            locals Object java/lang/String Object java/lang/String 
            stack Object org/json/JSONException 
        .end stack 
L50:    astore_2 
L51:    aconst_null 
L52:    areturn 
L53:    
    .end code 
.end method 

.method public static o00000 : (Ljava/lang/String;Ljava/lang/String;)Lcom/fs/graphics/Sprite; 
    .code stack 3 locals 4 
        .catch org/json/JSONException from L0 to L22 using L23 
L0:     getstatic Field com/fs/starfarer/settings/StarfarerSettings 'õÓ0000' Lorg/json/JSONObject; 
L3:     aload_0 
L4:     invokevirtual Method org/json/JSONObject getJSONObject (Ljava/lang/String;)Lorg/json/JSONObject; 
L7:     astore_2 
L8:     aload_2 
L9:     aload_1 
L10:    invokevirtual Method org/json/JSONObject getString (Ljava/lang/String;)Ljava/lang/String; 
L13:    astore_3 
L14:    new com/fs/graphics/Sprite 
L17:    dup 
L18:    aload_3 
L19:    invokespecial Method com/fs/graphics/Sprite <init> (Ljava/lang/String;)V 
L22:    areturn 

        .stack stack_1 Object org/json/JSONException 
L23:    astore_2 
L24:    aconst_null 
L25:    areturn 
L26:    
    .end code 
.end method 

.method public static 'Ó00000' : (Ljava/lang/String;Ljava/lang/String;)Lcom/fs/graphics/Object; 
    .code stack 7 locals 4 
        .catch org/json/JSONException from L0 to L52 using L53 
L0:     getstatic Field com/fs/starfarer/settings/StarfarerSettings 'õÓ0000' Lorg/json/JSONObject; 
L3:     aload_0 
L4:     invokevirtual Method org/json/JSONObject getJSONObject (Ljava/lang/String;)Lorg/json/JSONObject; 
L7:     astore_2 
L8:     aload_2 
L9:     aload_1 
L10:    invokevirtual Method org/json/JSONObject has (Ljava/lang/String;)Z 
L13:    ifne L42 
L16:    new java/lang/RuntimeException 
L19:    dup 
L20:    ldc_w 'Texture [%s] from category [%s] not found' 
L23:    iconst_2 
L24:    anewarray java/lang/Object 
L27:    dup 
L28:    iconst_0 
L29:    aload_1 
L30:    aastore 
L31:    dup 
L32:    iconst_1 
L33:    aload_0 
L34:    aastore 
L35:    invokestatic Method java/lang/String format (Ljava/lang/String;[Ljava/lang/Object;)Ljava/lang/String; 
L38:    invokespecial Method java/lang/RuntimeException <init> (Ljava/lang/String;)V 
L41:    athrow 

        .stack append Object org/json/JSONObject 
L42:    aload_2 
L43:    aload_1 
L44:    invokevirtual Method org/json/JSONObject getString (Ljava/lang/String;)Ljava/lang/String; 
L47:    astore_3 
L48:    aload_3 
L49:    invokestatic Method com/fs/graphics/oOoO 'Ò00000' (Ljava/lang/String;)Lcom/fs/graphics/Object; 
L52:    areturn 

        .stack full 
            locals Object java/lang/String Object java/lang/String 
            stack Object org/json/JSONException 
        .end stack 
L53:    astore_2 
L54:    aconst_null 
L55:    areturn 
L56:    
    .end code 
.end method 

.method public static 'öÕ0000' : ()V 
    .code stack 1 locals 0 
L0:     getstatic Field com/fs/starfarer/settings/StarfarerSettings 'ÖÖ0000' Ljava/util/Map; 
L3:     invokeinterface InterfaceMethod java/util/Map clear ()V 1 
L8:     getstatic Field com/fs/starfarer/settings/StarfarerSettings 'öô0000' Ljava/util/Map; 
L11:    invokeinterface InterfaceMethod java/util/Map clear ()V 1 
L16:    getstatic Field com/fs/starfarer/settings/StarfarerSettings float Ljava/util/Map; 
L19:    invokeinterface InterfaceMethod java/util/Map clear ()V 1 
L24:    getstatic Field com/fs/starfarer/settings/StarfarerSettings 'Ô00000' Ljava/util/Map; 
L27:    invokeinterface InterfaceMethod java/util/Map clear ()V 1 
L32:    return 
L33:    
    .end code 
.end method 

.method public static OO0000 : (Ljava/lang/String;)Ljava/awt/Color; 
    .code stack 3 locals 2 
L0:     getstatic Field com/fs/starfarer/settings/StarfarerSettings 'ÖÖ0000' Ljava/util/Map; 
L3:     aload_0 
L4:     invokeinterface InterfaceMethod java/util/Map containsKey (Ljava/lang/Object;)Z 2 
L9:     ifeq L25 
L12:    getstatic Field com/fs/starfarer/settings/StarfarerSettings 'ÖÖ0000' Ljava/util/Map; 
L15:    aload_0 
L16:    invokeinterface InterfaceMethod java/util/Map get (Ljava/lang/Object;)Ljava/lang/Object; 2 
L21:    checkcast java/awt/Color 
L24:    areturn 
        .catch org/json/JSONException from L25 to L45 using L46 

        .stack same 
L25:    getstatic Field com/fs/starfarer/settings/StarfarerSettings 'õØ0000' Lorg/json/JSONObject; 
L28:    aload_0 
L29:    invokestatic Method com/fs/starfarer/loading/String return (Lorg/json/JSONObject;Ljava/lang/String;)Ljava/awt/Color; 
L32:    astore_1 
L33:    getstatic Field com/fs/starfarer/settings/StarfarerSettings 'ÖÖ0000' Ljava/util/Map; 
L36:    aload_0 
L37:    aload_1 
L38:    invokeinterface InterfaceMethod java/util/Map put (Ljava/lang/Object;Ljava/lang/Object;)Ljava/lang/Object; 3 
L43:    pop 
L44:    aload_1 
L45:    areturn 

        .stack stack_1 Object org/json/JSONException 
L46:    astore_1 
L47:    new java/lang/RuntimeException 
L50:    dup 
L51:    aload_1 
L52:    invokespecial Method java/lang/RuntimeException <init> (Ljava/lang/Throwable;)V 
L55:    athrow 
L56:    
    .end code 
.end method 

.method public static new : (Ljava/lang/String;)Z 
    .code stack 2 locals 2 
L0:     getstatic Field com/fs/starfarer/settings/StarfarerSettings 'õØ0000' Lorg/json/JSONObject; 
L3:     ldc_w 'designTypeColors' 
L6:     invokevirtual Method org/json/JSONObject optJSONObject (Ljava/lang/String;)Lorg/json/JSONObject; 
L9:     astore_1 
L10:    aload_1 
L11:    ifnull L24 
L14:    aload_1 
L15:    aload_0 
L16:    invokevirtual Method org/json/JSONObject has (Ljava/lang/String;)Z 
L19:    ifeq L24 
L22:    iconst_1 
L23:    ireturn 

        .stack append Object org/json/JSONObject 
L24:    iconst_0 
L25:    ireturn 
L26:    
    .end code 
.end method 

.method public static oO0000 : (Ljava/lang/String;)Ljava/awt/Color; 
    .code stack 3 locals 3 
L0:     getstatic Field com/fs/starfarer/settings/StarfarerSettings 'Ø00000' Ljava/util/Map; 
L3:     aload_0 
L4:     invokeinterface InterfaceMethod java/util/Map containsKey (Ljava/lang/Object;)Z 2 
L9:     ifeq L25 
L12:    getstatic Field com/fs/starfarer/settings/StarfarerSettings 'Ø00000' Ljava/util/Map; 
L15:    aload_0 
L16:    invokeinterface InterfaceMethod java/util/Map get (Ljava/lang/Object;)Ljava/lang/Object; 2 
L21:    checkcast java/awt/Color 
L24:    areturn 
        .catch org/json/JSONException from L25 to L65 using L66 

        .stack same 
L25:    getstatic Field com/fs/starfarer/settings/StarfarerSettings 'õØ0000' Lorg/json/JSONObject; 
L28:    ldc_w 'designTypeColors' 
L31:    invokevirtual Method org/json/JSONObject getJSONObject (Ljava/lang/String;)Lorg/json/JSONObject; 
L34:    astore_1 
L35:    aload_1 
L36:    aload_0 
L37:    invokestatic Method com/fs/starfarer/loading/String return (Lorg/json/JSONObject;Ljava/lang/String;)Ljava/awt/Color; 
L40:    astore_2 
L41:    aload_1 
L42:    aload_0 
L43:    invokevirtual Method org/json/JSONObject has (Ljava/lang/String;)Z 
L46:    ifne L53 
L49:    invokestatic Method com/fs/starfarer/settings/StarfarerSettings 'Øo0000' ()Ljava/awt/Color; 
L52:    astore_2 

        .stack append Object org/json/JSONObject Object java/awt/Color 
L53:    getstatic Field com/fs/starfarer/settings/StarfarerSettings 'Ø00000' Ljava/util/Map; 
L56:    aload_0 
L57:    aload_2 
L58:    invokeinterface InterfaceMethod java/util/Map put (Ljava/lang/Object;Ljava/lang/Object;)Ljava/lang/Object; 3 
L63:    pop 
L64:    aload_2 
L65:    areturn 

        .stack full 
            locals Object java/lang/String 
            stack Object org/json/JSONException 
        .end stack 
L66:    astore_1 
L67:    invokestatic Method com/fs/starfarer/settings/StarfarerSettings 'Øo0000' ()Ljava/awt/Color; 
L70:    astore_2 
L71:    getstatic Field com/fs/starfarer/settings/StarfarerSettings 'Ø00000' Ljava/util/Map; 
L74:    aload_0 
L75:    aload_2 
L76:    invokeinterface InterfaceMethod java/util/Map put (Ljava/lang/Object;Ljava/lang/Object;)Ljava/lang/Object; 3 
L81:    pop 
L82:    aload_2 
L83:    areturn 
L84:    
    .end code 
.end method 

.method public static 'ö00000' : (Ljava/lang/String;)F 
    .code stack 3 locals 2 
L0:     getstatic Field com/fs/starfarer/settings/StarfarerSettings 'öô0000' Ljava/util/Map; 
L3:     aload_0 
L4:     invokeinterface InterfaceMethod java/util/Map containsKey (Ljava/lang/Object;)Z 2 
L9:     ifeq L28 
L12:    getstatic Field com/fs/starfarer/settings/StarfarerSettings 'öô0000' Ljava/util/Map; 
L15:    aload_0 
L16:    invokeinterface InterfaceMethod java/util/Map get (Ljava/lang/Object;)Ljava/lang/Object; 2 
L21:    checkcast java/lang/Float 
L24:    invokevirtual Method java/lang/Float floatValue ()F 
L27:    freturn 
        .catch org/json/JSONException from L28 to L52 using L53 

        .stack same 
L28:    getstatic Field com/fs/starfarer/settings/StarfarerSettings 'õØ0000' Lorg/json/JSONObject; 
L31:    aload_0 
L32:    invokevirtual Method org/json/JSONObject getDouble (Ljava/lang/String;)D 
L35:    d2f 
L36:    fstore_1 
L37:    getstatic Field com/fs/starfarer/settings/StarfarerSettings 'öô0000' Ljava/util/Map; 
L40:    aload_0 
L41:    fload_1 
L42:    invokestatic Method java/lang/Float valueOf (F)Ljava/lang/Float; 
L45:    invokeinterface InterfaceMethod java/util/Map put (Ljava/lang/Object;Ljava/lang/Object;)Ljava/lang/Object; 3 
L50:    pop 
L51:    fload_1 
L52:    freturn 

        .stack stack_1 Object org/json/JSONException 
L53:    astore_1 
L54:    new java/lang/RuntimeException 
L57:    dup 
L58:    aload_1 
L59:    invokespecial Method java/lang/RuntimeException <init> (Ljava/lang/Throwable;)V 
L62:    athrow 
L63:    
    .end code 
.end method 

.method public static o00000 : (Ljava/lang/String;F)F 
    .code stack 4 locals 3 
L0:     getstatic Field com/fs/starfarer/settings/StarfarerSettings 'öô0000' Ljava/util/Map; 
L3:     aload_0 
L4:     invokeinterface InterfaceMethod java/util/Map containsKey (Ljava/lang/Object;)Z 2 
L9:     ifeq L28 
L12:    getstatic Field com/fs/starfarer/settings/StarfarerSettings 'öô0000' Ljava/util/Map; 
L15:    aload_0 
L16:    invokeinterface InterfaceMethod java/util/Map get (Ljava/lang/Object;)Ljava/lang/Object; 2 
L21:    checkcast java/lang/Float 
L24:    invokevirtual Method java/lang/Float floatValue ()F 
L27:    freturn 

        .stack same 
L28:    getstatic Field com/fs/starfarer/settings/StarfarerSettings 'õØ0000' Lorg/json/JSONObject; 
L31:    aload_0 
L32:    fload_1 
L33:    f2d 
L34:    invokevirtual Method org/json/JSONObject optDouble (Ljava/lang/String;D)D 
L37:    d2f 
L38:    fstore_2 
L39:    getstatic Field com/fs/starfarer/settings/StarfarerSettings 'öô0000' Ljava/util/Map; 
L42:    aload_0 
L43:    fload_2 
L44:    invokestatic Method java/lang/Float valueOf (F)Ljava/lang/Float; 
L47:    invokeinterface InterfaceMethod java/util/Map put [u639] 3 
L52:    pop 
L53:    fload_2 
L54:    freturn 
L55:    
    .end code 
.end method 

.method public static new : (Ljava/lang/String;Z)V 
    .code stack 3 locals 3 
        .catch org/json/JSONException from L0 to L23 using L26 
L0:     getstatic Field com/fs/starfarer/settings/StarfarerSettings float Ljava/util/Map; 
L3:     aload_0 
L4:     iload_1 
L5:     invokestatic Method java/lang/Boolean valueOf (Z)Ljava/lang/Boolean; 
L8:     invokeinterface InterfaceMethod java/util/Map put [u639] 3 
L13:    pop 
L14:    getstatic Field com/fs/starfarer/settings/StarfarerSettings 'õØ0000' Lorg/json/JSONObject; 
L17:    aload_0 
L18:    iload_1 
L19:    invokevirtual Method org/json/JSONObject put (Ljava/lang/String;Z)Lorg/json/JSONObject; 
L22:    pop 
L23:    goto L36 

        .stack stack_1 Object org/json/JSONException 
L26:    astore_2 
L27:    new java/lang/RuntimeException 
L30:    dup 
L31:    aload_2 
L32:    invokespecial Method java/lang/RuntimeException <init> (Ljava/lang/Throwable;)V 
L35:    athrow 

        .stack same 
L36:    return 
L37:    
    .end code 
.end method 

.method public static new : (Ljava/lang/String;F)V 
    .code stack 4 locals 3 
        .catch org/json/JSONException from L0 to L24 using L27 
L0:     getstatic Field com/fs/starfarer/settings/StarfarerSettings 'öô0000' Ljava/util/Map; 
L3:     aload_0 
L4:     fload_1 
L5:     invokestatic Method java/lang/Float valueOf (F)Ljava/lang/Float; 
L8:     invokeinterface InterfaceMethod java/util/Map put [u639] 3 
L13:    pop 
L14:    getstatic Field com/fs/starfarer/settings/StarfarerSettings 'õØ0000' Lorg/json/JSONObject; 
L17:    aload_0 
L18:    fload_1 
L19:    f2d 
L20:    invokevirtual Method org/json/JSONObject put (Ljava/lang/String;D)Lorg/json/JSONObject; 
L23:    pop 
L24:    goto L37 

        .stack stack_1 Object org/json/JSONException 
L27:    astore_2 
L28:    new java/lang/RuntimeException 
L31:    dup 
L32:    aload_2 
L33:    invokespecial Method java/lang/RuntimeException <init> (Ljava/lang/Throwable;)V 
L36:    athrow 

        .stack same 
L37:    return 
L38:    
    .end code 
.end method 

.method public static 'new.String' : ()Z 
    .code stack 1 locals 0 
L0:     invokestatic Method com/fs/starfarer/settings/StarfarerSettings while ()Z 
L3:     ireturn 
L4:     
    .end code 
.end method 

.method public static 'float.new' : ()I 
    .code stack 1 locals 0 
L0:     ldc_w 'startingCommandPoints' 
L3:     invokestatic Method com/fs/starfarer/settings/StarfarerSettings 'ö00000' (Ljava/lang/String;)F 
L6:     f2i 
L7:     ireturn 
L8:     
    .end code 
.end method 

.method public static 'interface.new' : ()Z 
    .code stack 1 locals 0 
L0:     ldc_w 'undecoratedWindow' 
L3:     invokestatic Method com/fs/starfarer/settings/StarfarerSettings class (Ljava/lang/String;)Z 
L6:     ireturn 
L7:     
    .end code 
.end method 

.method public static class : (Ljava/lang/String;)Z 
    .code stack 3 locals 2 
L0:     getstatic Field com/fs/starfarer/settings/StarfarerSettings float Ljava/util/Map; 
L3:     aload_0 
L4:     invokeinterface InterfaceMethod java/util/Map containsKey (Ljava/lang/Object;)Z 2 
L9:     ifeq L28 
L12:    getstatic Field com/fs/starfarer/settings/StarfarerSettings float Ljava/util/Map; 
L15:    aload_0 
L16:    invokeinterface InterfaceMethod java/util/Map get (Ljava/lang/Object;)Ljava/lang/Object; 2 
L21:    checkcast java/lang/Boolean 
L24:    invokevirtual Method java/lang/Boolean booleanValue ()Z 
L27:    ireturn 
        .catch org/json/JSONException from L28 to L51 using L52 

        .stack same 
L28:    getstatic Field com/fs/starfarer/settings/StarfarerSettings 'õØ0000' Lorg/json/JSONObject; 
L31:    aload_0 
L32:    invokevirtual Method org/json/JSONObject getBoolean (Ljava/lang/String;)Z 
L35:    istore_1 
L36:    getstatic Field com/fs/starfarer/settings/StarfarerSettings float Ljava/util/Map; 
L39:    aload_0 
L40:    iload_1 
L41:    invokestatic Method java/lang/Boolean valueOf (Z)Ljava/lang/Boolean; 
L44:    invokeinterface InterfaceMethod java/util/Map put [u639] 3 
L49:    pop 
L50:    iload_1 
L51:    ireturn 

        .stack stack_1 Object org/json/JSONException 
L52:    astore_1 
L53:    new java/lang/RuntimeException 
L56:    dup 
L57:    aload_1 
L58:    invokespecial Method java/lang/RuntimeException <init> (Ljava/lang/Throwable;)V 
L61:    athrow 
L62:    
    .end code 
.end method 

.method public static o00000 : (Ljava/lang/String;Z)Z 
    .code stack 3 locals 3 
L0:     getstatic Field com/fs/starfarer/settings/StarfarerSettings float Ljava/util/Map; 
L3:     aload_0 
L4:     invokeinterface InterfaceMethod java/util/Map containsKey (Ljava/lang/Object;)Z 2 
L9:     ifeq L28 
L12:    getstatic Field com/fs/starfarer/settings/StarfarerSettings float Ljava/util/Map; 
L15:    aload_0 
L16:    invokeinterface InterfaceMethod java/util/Map get (Ljava/lang/Object;)Ljava/lang/Object; 2 
L21:    checkcast java/lang/Boolean 
L24:    invokevirtual Method java/lang/Boolean booleanValue ()Z 
L27:    ireturn 

        .stack same 
L28:    getstatic Field com/fs/starfarer/settings/StarfarerSettings 'õØ0000' Lorg/json/JSONObject; 
L31:    aload_0 
L32:    iload_1 
L33:    invokevirtual Method org/json/JSONObject optBoolean (Ljava/lang/String;Z)Z 
L36:    istore_2 
L37:    getstatic Field com/fs/starfarer/settings/StarfarerSettings float Ljava/util/Map; 
L40:    aload_0 
L41:    iload_2 
L42:    invokestatic Method java/lang/Boolean valueOf (Z)Ljava/lang/Boolean; 
L45:    invokeinterface InterfaceMethod java/util/Map put [u639] 3 
L50:    pop 
L51:    iload_2 
L52:    ireturn 
L53:    
    .end code 
.end method 

.method public static while : (Ljava/lang/String;)Ljava/lang/String; 
    .code stack 3 locals 2 
        .catch org/json/JSONException from L0 to L7 using L8 
L0:     getstatic Field com/fs/starfarer/settings/StarfarerSettings 'õØ0000' Lorg/json/JSONObject; 
L3:     aload_0 
L4:     invokevirtual Method org/json/JSONObject getString (Ljava/lang/String;)Ljava/lang/String; 
L7:     areturn 

        .stack stack_1 Object org/json/JSONException 
L8:     astore_1 
L9:     new java/lang/RuntimeException 
L12:    dup 
L13:    aload_1 
L14:    invokespecial Method java/lang/RuntimeException <init> (Ljava/lang/Throwable;)V 
L17:    athrow 
L18:    
    .end code 
.end method 

.method public static null : (Ljava/lang/String;)Ljava/lang/String; 
    .code stack 3 locals 1 
L0:     getstatic Field com/fs/starfarer/settings/StarfarerSettings 'õØ0000' Lorg/json/JSONObject; 
L3:     aload_0 
L4:     aconst_null 
L5:     invokevirtual Method org/json/JSONObject optString (Ljava/lang/String;Ljava/lang/String;)Ljava/lang/String; 
L8:     areturn 
L9:     
    .end code 
.end method 

.method public static 'ö00000' : ()Z 
    .code stack 1 locals 0 
L0:     getstatic Field com/fs/starfarer/settings/StarfarerSettings 'õo0000' Z 
L3:     ireturn 
L4:     
    .end code 
.end method 

.method public static 'ÔO0000' : (Z)V 
    .code stack 1 locals 1 
L0:     iload_0 
L1:     putstatic Field com/fs/starfarer/settings/StarfarerSettings 'õo0000' Z 
L4:     return 
L5:     
    .end code 
.end method 

.method public static 'OÓ0000' : ()Z 
    .code stack 1 locals 0 
L0:     ldc_w 'devMode' 
L3:     invokestatic Method com/fs/starfarer/settings/StarfarerSettings class (Ljava/lang/String;)Z 
L6:     ireturn 
L7:     
    .end code 
.end method 

.method public static 'class.super' : ()Z 
    .code stack 1 locals 0 
L0:     ldc_w 'autosaveFeatureEnabled' 
L3:     invokestatic Method com/fs/starfarer/settings/StarfarerSettings class (Ljava/lang/String;)Z 
L6:     ireturn 
L7:     
    .end code 
.end method 

.method public static 'class.Object' : ()F 
    .code stack 1 locals 0 
L0:     ldc_w 'fps' 
L3:     invokestatic Method com/fs/starfarer/settings/StarfarerSettings 'ö00000' (Ljava/lang/String;)F 
L6:     freturn 
L7:     
    .end code 
.end method

.method public static getFPS : ()F
    .code stack 1 locals 0
L0:     ldc 'fps'
L2:     invokestatic Method com/fs/starfarer/settings/StarfarerSettings 'ö00000' (Ljava/lang/String;)F
L5:     freturn
L6:
        .linenumbertable
            L0 11
        .end linenumbertable
    .end code
.end method

.method public static 'ÖÖ0000' : ()Z 
    .code stack 1 locals 0 
L0:     getstatic Field com/fs/starfarer/settings/StarfarerSettings 'float.return' Z 
L3:     ireturn 
L4:     
    .end code 
.end method 

.method public static 'Ó00000' : (Z)V 
    .code stack 1 locals 1 
L0:     iload_0 
L1:     putstatic Field com/fs/starfarer/settings/StarfarerSettings 'float.return' Z 
L4:     return 
L5:     
    .end code 
.end method 

.method public static 'float.super' : ()Z 
    .code stack 1 locals 0 
L0:     ldc_w 'vsync' 
L3:     invokestatic Method com/fs/starfarer/settings/StarfarerSettings class (Ljava/lang/String;)Z 
L6:     ireturn 
L7:     
    .end code 
.end method 

.method public static 'while.new' : ()F 
    .code stack 1 locals 0 
L0:     getstatic Field com/fs/starfarer/settings/StarfarerSettings 'õÒ0000' F 
L3:     freturn 
L4:     
    .end code 
.end method 

.method public static 'Ó00000' : (I)V 
    .code stack 1 locals 1 
L0:     iload_0 
L1:     i2f 
L2:     putstatic Field com/fs/starfarer/settings/StarfarerSettings 'õÒ0000' F 
L5:     return 
L6:     
    .end code 
.end method 

.method public static 'öÒ0000' : ()F 
    .code stack 1 locals 0 
L0:     getstatic Field com/fs/starfarer/settings/StarfarerSettings 'new.return' F 
L3:     freturn 
L4:     
    .end code 
.end method 

.method public static o00000 : (I)V 
    .code stack 1 locals 1 
L0:     iload_0 
L1:     i2f 
L2:     putstatic Field com/fs/starfarer/settings/StarfarerSettings 'new.return' F 
L5:     return 
L6:     
    .end code 
.end method 

.method public static 'ÖO0000' : ()Z 
    .code stack 2 locals 0 
L0:     getstatic Field com/fs/starfarer/settings/StarfarerSettings 'õØ0000' Lorg/json/JSONObject; 
L3:     ldc_w 'windowLocationX' 
L6:     invokevirtual Method org/json/JSONObject has (Ljava/lang/String;)Z 
L9:     ifeq L26 
L12:    getstatic Field com/fs/starfarer/settings/StarfarerSettings 'õØ0000' Lorg/json/JSONObject; 
L15:    ldc_w 'windowLocationY' 
L18:    invokevirtual Method org/json/JSONObject has (Ljava/lang/String;)Z 
L21:    ifeq L26 
L24:    iconst_1 
L25:    ireturn 

        .stack same 
L26:    iconst_0 
L27:    ireturn 
L28:    
    .end code 
.end method 

.method public static 'float.class' : ()F 
    .code stack 1 locals 0 
L0:     ldc_w 'windowLocationX' 
L3:     invokestatic Method com/fs/starfarer/settings/StarfarerSettings 'ö00000' (Ljava/lang/String;)F 
L6:     freturn 
L7:     
    .end code 
.end method 

.method public static null : ()F 
    .code stack 1 locals 0 
L0:     ldc_w 'windowLocationY' 
L3:     invokestatic Method com/fs/starfarer/settings/StarfarerSettings 'ö00000' (Ljava/lang/String;)F 
L6:     freturn 
L7:     
    .end code 
.end method 

.method public static 'ØØ0000' : ()F 
    .code stack 1 locals 0 
L0:     ldc_w 'crLossMultForRetreatInLoss' 
L3:     invokestatic Method com/fs/starfarer/settings/StarfarerSettings 'ö00000' (Ljava/lang/String;)F 
L6:     freturn 
L7:     
    .end code 
.end method 

.method public static 'ØÓ0000' : ()F 
    .code stack 1 locals 0 
L0:     ldc_w 'crLossMultForFlameout' 
L3:     invokestatic Method com/fs/starfarer/settings/StarfarerSettings 'ö00000' (Ljava/lang/String;)F 
L6:     freturn 
L7:     
    .end code 
.end method 

.method public static 'null.String' : ()F 
    .code stack 1 locals 0 
L0:     ldc_w 'crLossMultForWeaponDisabled' 
L3:     invokestatic Method com/fs/starfarer/settings/StarfarerSettings 'ö00000' (Ljava/lang/String;)F 
L6:     freturn 
L7:     
    .end code 
.end method 

.method public static 'class.new' : ()F 
    .code stack 1 locals 0 
L0:     ldc_w 'crLossMultForMissilesFired' 
L3:     invokestatic Method com/fs/starfarer/settings/StarfarerSettings 'ö00000' (Ljava/lang/String;)F 
L6:     freturn 
L7:     
    .end code 
.end method 

.method public static oO0000 : ()F 
    .code stack 1 locals 0 
L0:     ldc_w 'crLossMultForReservesInLoss' 
L3:     invokestatic Method com/fs/starfarer/settings/StarfarerSettings 'ö00000' (Ljava/lang/String;)F 
L6:     freturn 
L7:     
    .end code 
.end method 

.method public static 'õØ0000' : ()F 
    .code stack 1 locals 0 
L0:     ldc_w 'crLossMultForRefit' 
L3:     invokestatic Method com/fs/starfarer/settings/StarfarerSettings 'ö00000' (Ljava/lang/String;)F 
L6:     freturn 
L7:     
    .end code 
.end method 

.method public static 'oÕ0000' : ()F 
    .code stack 1 locals 0 
L0:     ldc_w 'maxNoObjectiveBattleSize' 
L3:     invokestatic Method com/fs/starfarer/settings/StarfarerSettings 'ö00000' (Ljava/lang/String;)F 
L6:     freturn 
L7:     
    .end code 
.end method 

.method public static 'interface.super' : ()F 
    .code stack 1 locals 0 
L0:     ldc_w 'minBattleSize' 
L3:     invokestatic Method com/fs/starfarer/settings/StarfarerSettings 'ö00000' (Ljava/lang/String;)F 
L6:     freturn 
L7:     
    .end code 
.end method 

.method public static 'öØ0000' : ()F 
    .code stack 1 locals 0 
L0:     ldc_w 'maxBattleSize' 
L3:     invokestatic Method com/fs/starfarer/settings/StarfarerSettings 'ö00000' (Ljava/lang/String;)F 
L6:     freturn 
L7:     
    .end code 
.end method 

.method public static 'õ00000' : ()Z 
    .code stack 1 locals 0 
L0:     getstatic Field com/fs/starfarer/settings/StarfarerSettings 'OÒ0000' Z 
L3:     ifeq L14 
L6:     getstatic Field com/fs/starfarer/combat/CombatMain AL_DESTROYED Z 
L9:     ifne L14 
L12:    iconst_1 
L13:    ireturn 

        .stack same 
L14:    iconst_0 
L15:    ireturn 
L16:    
    .end code 
.end method 

.method public static while : (Z)V 
    .code stack 1 locals 1 
L0:     iload_0 
L1:     putstatic Field com/fs/starfarer/settings/StarfarerSettings 'OÒ0000' Z 
L4:     return 
L5:     
    .end code 
.end method 

.method public static 'oÖ0000' : ()Lcom/fs/starfarer/settings/A; 
    .code stack 1 locals 0 
L0:     getstatic Field com/fs/starfarer/settings/StarfarerSettings 'ÔO0000' Lcom/fs/starfarer/settings/A; 
L3:     areturn 
L4:     
    .end code 
.end method 

.method public static float : ()I 
    .code stack 1 locals 0 
L0:     getstatic Field com/fs/starfarer/settings/StarfarerSettings 'new.super' I 
L3:     ireturn 
L4:     
    .end code 
.end method 

.method public static 'Ô00000' : (I)V 
    .code stack 1 locals 1 
L0:     iload_0 
L1:     putstatic Field com/fs/starfarer/settings/StarfarerSettings 'new.super' I 
L4:     return 
L5:     
    .end code 
.end method 

.method public static 'ÓÖ0000' : ()Z 
    .code stack 1 locals 0 
L0:     getstatic Field com/fs/starfarer/settings/StarfarerSettings 'Öô0000' Z 
L3:     ifeq L14 
L6:     getstatic Field com/fs/starfarer/combat/CombatMain AL_DESTROYED Z 
L9:     ifne L14 
L12:    iconst_1 
L13:    ireturn 

        .stack same 
L14:    iconst_0 
L15:    ireturn 
L16:    
    .end code 
.end method 

.method public static 'Ö00000' : (Z)V 
    .code stack 1 locals 1 
L0:     iload_0 
L1:     putstatic Field com/fs/starfarer/settings/StarfarerSettings 'Öô0000' Z 
L4:     return 
L5:     
    .end code 
.end method 

.method public static 'ÔØ0000' : ()F 
    .code stack 1 locals 0 
L0:     getstatic Field com/fs/starfarer/settings/StarfarerSettings 'õÔ0000' F 
L3:     freturn 
L4:     
    .end code 
.end method 

.method public static class : (F)V 
    .code stack 1 locals 1 
L0:     fload_0 
L1:     putstatic Field com/fs/starfarer/settings/StarfarerSettings 'õÔ0000' F 
L4:     return 
L5:     
    .end code 
.end method 

.method public static 'while.class' : ()F 
    .code stack 1 locals 0 
L0:     getstatic Field com/fs/starfarer/settings/StarfarerSettings 'Ôô0000' F 
L3:     freturn 
L4:     
    .end code 
.end method 

.method public static new : (F)V 
    .code stack 1 locals 1 
L0:     fload_0 
L1:     putstatic Field com/fs/starfarer/settings/StarfarerSettings 'Ôô0000' F 
L4:     return 
L5:     
    .end code 
.end method 

.method public static 'oÒ0000' : ()I 
    .code stack 2 locals 0 
L0:     getstatic Field com/fs/starfarer/settings/StarfarerSettings 'interface' I 
L3:     i2f 
L4:     invokestatic Method com/fs/starfarer/settings/StarfarerSettings 'öØ0000' ()F 
L7:     fcmpl 
L8:     ifle L16 
L11:    invokestatic Method com/fs/starfarer/settings/StarfarerSettings 'öØ0000' ()F 
L14:    f2i 
L15:    ireturn 

        .stack same 
L16:    getstatic Field com/fs/starfarer/settings/StarfarerSettings 'interface' I 
L19:    i2f 
L20:    invokestatic Method com/fs/starfarer/settings/StarfarerSettings 'interface.super' ()F 
L23:    fcmpg 
L24:    ifge L32 
L27:    invokestatic Method com/fs/starfarer/settings/StarfarerSettings 'interface.super' ()F 
L30:    f2i 
L31:    ireturn 

        .stack same 
L32:    getstatic Field com/fs/starfarer/settings/StarfarerSettings 'interface' I 
L35:    ireturn 
L36:    
    .end code 
.end method 

.method public static new : (I)V 
    .code stack 1 locals 1 
L0:     iload_0 
L1:     putstatic Field com/fs/starfarer/settings/StarfarerSettings 'interface' I 
L4:     return 
L5:     
    .end code 
.end method 

.method public static 'new.super' : ()Lcom/fs/starfarer/api/SettingsAPI; 
    .code stack 2 locals 0 
L0:     new com/fs/starfarer/settings/StarfarerSettings$1 
L3:     dup 
L4:     invokespecial Method com/fs/starfarer/settings/StarfarerSettings$1 <init> ()V 
L7:     areturn 
L8:     
    .end code 
.end method 

.method public static 'ÖÕ0000' : ()F 
    .code stack 1 locals 0 
L0:     ldc_w 'baseNumOfficers' 
L3:     invokestatic Method com/fs/starfarer/settings/StarfarerSettings 'ö00000' (Ljava/lang/String;)F 
L6:     freturn 
L7:     
    .end code 
.end method 

.method public static 'Øo0000' : ()Ljava/awt/Color; 
    .code stack 2 locals 1 
L0:     getstatic Field com/fs/starfarer/settings/StarfarerSettings 'ÓÒ0000' Ljava/awt/Color; 
L3:     ifnonnull L26 
L6:     ldc_w Class com/fs/starfarer/loading/O0oO 
L9:     ldc_w 'player' 
L12:    invokestatic Method com/fs/starfarer/loading/SpecStore o00000 (Ljava/lang/Class;Ljava/lang/String;)Ljava/lang/Object; 
L15:    checkcast com/fs/starfarer/loading/O0oO 
L18:    astore_0 
L19:    aload_0 
L20:    invokevirtual Method com/fs/starfarer/loading/O0oO getBaseUIColor ()Ljava/awt/Color; 
L23:    putstatic Field com/fs/starfarer/settings/StarfarerSettings 'ÓÒ0000' Ljava/awt/Color; 

        .stack same 
L26:    getstatic Field com/fs/starfarer/settings/StarfarerSettings 'ÓÒ0000' Ljava/awt/Color; 
L29:    areturn 
L30:    
    .end code 
.end method 

.method public static 'Ö00000' : ()Ljava/awt/Color; 
    .code stack 2 locals 1 
L0:     getstatic Field com/fs/starfarer/settings/StarfarerSettings 'null.Object' Ljava/awt/Color; 
L3:     ifnonnull L26 
L6:     ldc_w Class com/fs/starfarer/loading/O0oO 
L9:     ldc_w 'player' 
L12:    invokestatic Method com/fs/starfarer/loading/SpecStore o00000 (Ljava/lang/Class;Ljava/lang/String;)Ljava/lang/Object; 
L15:    checkcast com/fs/starfarer/loading/O0oO 
L18:    astore_0 
L19:    aload_0 
L20:    invokevirtual Method com/fs/starfarer/loading/O0oO getDarkUIColor ()Ljava/awt/Color; 
L23:    putstatic Field com/fs/starfarer/settings/StarfarerSettings 'null.Object' Ljava/awt/Color; 

        .stack same 
L26:    getstatic Field com/fs/starfarer/settings/StarfarerSettings 'null.Object' Ljava/awt/Color; 
L29:    areturn 
L30:    
    .end code 
.end method 

.method public static 'null.Object' : ()Ljava/awt/Color; 
    .code stack 2 locals 1 
L0:     getstatic Field com/fs/starfarer/settings/StarfarerSettings 'ÓØ0000' Ljava/awt/Color; 
L3:     ifnonnull L26 
L6:     ldc_w Class com/fs/starfarer/loading/O0oO 
L9:     ldc_w 'player' 
L12:    invokestatic Method com/fs/starfarer/loading/SpecStore o00000 (Ljava/lang/Class;Ljava/lang/String;)Ljava/lang/Object; 
L15:    checkcast com/fs/starfarer/loading/O0oO 
L18:    astore_0 
L19:    aload_0 
L20:    invokevirtual Method com/fs/starfarer/loading/O0oO getBrightUIColor ()Ljava/awt/Color; 
L23:    putstatic Field com/fs/starfarer/settings/StarfarerSettings 'ÓØ0000' Ljava/awt/Color; 

        .stack same 
L26:    getstatic Field com/fs/starfarer/settings/StarfarerSettings 'ÓØ0000' Ljava/awt/Color; 
L29:    areturn 
L30:    
    .end code 
.end method 

.method public static 'interface.class' : ()Ljava/awt/Color; 
    .code stack 2 locals 1 
L0:     getstatic Field com/fs/starfarer/settings/StarfarerSettings 'ØÔ0000' Ljava/awt/Color; 
L3:     ifnonnull L26 
L6:     ldc_w Class com/fs/starfarer/loading/O0oO 
L9:     ldc_w 'player' 
L12:    invokestatic Method com/fs/starfarer/loading/SpecStore o00000 (Ljava/lang/Class;Ljava/lang/String;)Ljava/lang/Object; 
L15:    checkcast com/fs/starfarer/loading/O0oO 
L18:    astore_0 
L19:    aload_0 
L20:    invokevirtual Method com/fs/starfarer/loading/O0oO getGridUIColor ()Ljava/awt/Color; 
L23:    putstatic Field com/fs/starfarer/settings/StarfarerSettings 'ØÔ0000' Ljava/awt/Color; 

        .stack same 
L26:    getstatic Field com/fs/starfarer/settings/StarfarerSettings 'ØÔ0000' Ljava/awt/Color; 
L29:    areturn 
L30:    
    .end code 
.end method 

.method public static 'while.String' : ()Z 
    .code stack 1 locals 0 
L0:     getstatic Field com/fs/starfarer/settings/StarfarerSettings 'õ00000' Z 
L3:     ireturn 
L4:     
    .end code 
.end method 

.method public static 'Ô00000' : (Z)V 
    .code stack 1 locals 1 
L0:     iload_0 
L1:     putstatic Field com/fs/starfarer/settings/StarfarerSettings 'õ00000' Z 
L4:     return 
L5:     
    .end code 
.end method 

.method public static 'Óo0000' : ()Z 
    .code stack 1 locals 0 
L0:     getstatic Field com/fs/starfarer/settings/StarfarerSettings 'oô0000' Z 
L3:     ireturn 
L4:     
    .end code 
.end method 

.method public static 'õ00000' : (Z)V 
    .code stack 1 locals 1 
L0:     iload_0 
L1:     putstatic Field com/fs/starfarer/settings/StarfarerSettings 'oô0000' Z 
L4:     return 
L5:     
    .end code 
.end method 

.method public static 'ÔÔ0000' : ()Z 
    .code stack 1 locals 0 
L0:     getstatic Field com/fs/starfarer/settings/StarfarerSettings new Z 
L3:     ireturn 
L4:     
    .end code 
.end method 

.method public static 'Ø00000' : (Z)V 
    .code stack 1 locals 1 
L0:     iload_0 
L1:     putstatic Field com/fs/starfarer/settings/StarfarerSettings new Z 
L4:     return 
L5:     
    .end code 
.end method 

.method public static Oo0000 : ()Z 
    .code stack 1 locals 0 
L0:     getstatic Field com/fs/starfarer/settings/StarfarerSettings class Z 
L3:     ireturn 
L4:     
    .end code 
.end method 

.method public static 'ö00000' : (Z)V 
    .code stack 1 locals 1 
L0:     iload_0 
L1:     putstatic Field com/fs/starfarer/settings/StarfarerSettings class Z 
L4:     return 
L5:     
    .end code 
.end method 

.method public static 'OÔ0000' : ()Ljava/lang/String; 
    .code stack 1 locals 0 
L0:     getstatic Field com/fs/starfarer/settings/StarfarerSettings 'interface.class' Ljava/lang/String; 
L3:     areturn 
L4:     
    .end code 
.end method 

.method public static float : (Ljava/lang/String;)V 
    .code stack 1 locals 1 
L0:     aload_0 
L1:     putstatic Field com/fs/starfarer/settings/StarfarerSettings 'interface.class' Ljava/lang/String; 
L4:     return 
L5:     
    .end code 
.end method 

.method public static 'ÓÓ0000' : ()Z 
    .code stack 1 locals 0 
L0:     getstatic Field com/fs/starfarer/settings/StarfarerSettings 'OØ0000' Z 
L3:     ireturn 
L4:     
    .end code 
.end method 

.method public static o00000 : (Z)V 
    .code stack 1 locals 1 
L0:     iload_0 
L1:     putstatic Field com/fs/starfarer/settings/StarfarerSettings 'OØ0000' Z 
L4:     return 
L5:     
    .end code 
.end method 

.method public static 'õ00000' : (Ljava/lang/String;)V 
    .code stack 3 locals 1 
L0:     aload_0 
L1:     invokevirtual Method java/lang/String trim ()Ljava/lang/String; 
L4:     astore_0 
L5:     aload_0 
L6:     ifnull L80 
L9:     aload_0 
L10:    ldc_w '..' 
L13:    invokevirtual Method java/lang/String contains (Ljava/lang/CharSequence;)Z 
L16:    ifne L69 
L19:    aload_0 
L20:    ldc_w '/' 
L23:    invokevirtual Method java/lang/String startsWith (Ljava/lang/String;)Z 
L26:    ifne L69 
L29:    aload_0 
L30:    ldc_w '\\' 
L33:    invokevirtual Method java/lang/String contains (Ljava/lang/CharSequence;)Z 
L36:    ifne L69 
L39:    aload_0 
L40:    ldc_w 'c:' 
L43:    invokevirtual Method java/lang/String contains (Ljava/lang/CharSequence;)Z 
L46:    ifne L69 
L49:    aload_0 
L50:    ldc_w 'd:' 
L53:    invokevirtual Method java/lang/String contains (Ljava/lang/CharSequence;)Z 
L56:    ifne L69 
L59:    aload_0 
L60:    ldc_w ':' 
L63:    invokevirtual Method java/lang/String contains (Ljava/lang/CharSequence;)Z 
L66:    ifeq L80 

        .stack same_extended 
L69:    new java/lang/RuntimeException 
L72:    dup 
L73:    ldc_w '.. and starting with a / are not allowed in filenames. Also, use / instead of \\.' 
L76:    invokespecial Method java/lang/RuntimeException <init> (Ljava/lang/String;)V 
L79:    athrow 

        .stack same 
L80:    return 
L81:    
    .end code 
.end method 

.method public static 'ÔÒ0000' : ()Z 
    .code stack 1 locals 0 
L0:     getstatic Field com/fs/starfarer/settings/StarfarerSettings 'OÔ0000' Z 
L3:     ireturn 
L4:     
    .end code 
.end method 

.method public static oO0000 : (Z)V 
    .code stack 1 locals 1 
L0:     iload_0 
L1:     putstatic Field com/fs/starfarer/settings/StarfarerSettings 'OÔ0000' Z 
L4:     return 
L5:     
    .end code 
.end method 

.method static synthetic 'ØÔ0000' : ()[I 
    .code stack 3 locals 1 
L0:     getstatic Field com/fs/starfarer/settings/StarfarerSettings 'Ôo0000' [I 
L3:     dup 
L4:     ifnull L8 
L7:     areturn 

        .stack stack_1 Object [I 
L8:     pop 
L9:     invokestatic Method com/fs/starfarer/api/combat/ShipAPI$HullSize values ()[Lcom/fs/starfarer/api/combat/ShipAPI$HullSize; 
L12:    arraylength 
L13:    newarray int 
L15:    astore_0 
        .catch java/lang/NoSuchFieldError from L16 to L26 using L29 
L16:    aload_0 
L17:    getstatic Field com/fs/starfarer/api/combat/ShipAPI$HullSize CAPITAL_SHIP Lcom/fs/starfarer/api/combat/ShipAPI$HullSize; 
L20:    invokevirtual Method com/fs/starfarer/api/combat/ShipAPI$HullSize ordinal ()I 
L23:    bipush 6 
L25:    iastore 
L26:    goto L30 

        .stack full 
            locals Object [I 
            stack Object java/lang/NoSuchFieldError 
        .end stack 
L29:    pop 
        .catch java/lang/NoSuchFieldError from L30 to L39 using L42 

        .stack same 
L30:    aload_0 
L31:    getstatic Field com/fs/starfarer/api/combat/ShipAPI$HullSize CRUISER Lcom/fs/starfarer/api/combat/ShipAPI$HullSize; 
L34:    invokevirtual Method com/fs/starfarer/api/combat/ShipAPI$HullSize ordinal ()I 
L37:    iconst_5 
L38:    iastore 
L39:    goto L43 

        .stack stack_1 Object java/lang/NoSuchFieldError 
L42:    pop 
        .catch java/lang/NoSuchFieldError from L43 to L52 using L55 

        .stack same 
L43:    aload_0 
L44:    getstatic Field com/fs/starfarer/api/combat/ShipAPI$HullSize DEFAULT Lcom/fs/starfarer/api/combat/ShipAPI$HullSize; 
L47:    invokevirtual Method com/fs/starfarer/api/combat/ShipAPI$HullSize ordinal ()I 
L50:    iconst_1 
L51:    iastore 
L52:    goto L56 

        .stack stack_1 Object java/lang/NoSuchFieldError 
L55:    pop 
        .catch java/lang/NoSuchFieldError from L56 to L65 using L68 

        .stack same 
L56:    aload_0 
L57:    getstatic Field com/fs/starfarer/api/combat/ShipAPI$HullSize DESTROYER Lcom/fs/starfarer/api/combat/ShipAPI$HullSize; 
L60:    invokevirtual Method com/fs/starfarer/api/combat/ShipAPI$HullSize ordinal ()I 
L63:    iconst_4 
L64:    iastore 
L65:    goto L69 

        .stack stack_1 Object java/lang/NoSuchFieldError 
L68:    pop 
        .catch java/lang/NoSuchFieldError from L69 to L78 using L81 

        .stack same 
L69:    aload_0 
L70:    getstatic Field com/fs/starfarer/api/combat/ShipAPI$HullSize FIGHTER Lcom/fs/starfarer/api/combat/ShipAPI$HullSize; 
L73:    invokevirtual Method com/fs/starfarer/api/combat/ShipAPI$HullSize ordinal ()I 
L76:    iconst_2 
L77:    iastore 
L78:    goto L82 

        .stack stack_1 Object java/lang/NoSuchFieldError 
L81:    pop 
        .catch java/lang/NoSuchFieldError from L82 to L91 using L94 

        .stack same 
L82:    aload_0 
L83:    getstatic Field com/fs/starfarer/api/combat/ShipAPI$HullSize FRIGATE Lcom/fs/starfarer/api/combat/ShipAPI$HullSize; 
L86:    invokevirtual Method com/fs/starfarer/api/combat/ShipAPI$HullSize ordinal ()I 
L89:    iconst_3 
L90:    iastore 
L91:    goto L95 

        .stack stack_1 Object java/lang/NoSuchFieldError 
L94:    pop 

        .stack same 
L95:    aload_0 
L96:    dup 
L97:    putstatic Field com/fs/starfarer/settings/StarfarerSettings 'Ôo0000' [I 
L100:   areturn 
L101:   
    .end code 
.end method 
.innerclasses 
    com/fs/starfarer/api/combat/ShipAPI$HullSize com/fs/starfarer/api/combat/ShipAPI HullSize public static final enum 
    com/fs/starfarer/loading/ResourceLoaderState$o com/fs/starfarer/loading/ResourceLoaderState o public static final enum 
    com/fs/starfarer/settings/StarfarerSettings$1 [0] [0] 
    com/fs/starfarer/settings/StarfarerSettings$o com/fs/starfarer/settings/StarfarerSettings o private static 
    com/fs/starfarer/settings/StarfarerSettings$Oo com/fs/starfarer/settings/StarfarerSettings Oo public static 
.end innerclasses 
.nestmembers com/fs/starfarer/settings/StarfarerSettings$1 com/fs/starfarer/settings/StarfarerSettings$1$1 com/fs/starfarer/settings/StarfarerSettings$1$2 com/fs/starfarer/settings/StarfarerSettings$o com/fs/starfarer/settings/StarfarerSettings$Oo 
.const [u639] = Utf8 (Ljava/lang/Object;Ljava/lang/Object;)Ljava/lang/Object; 
.end class 
